[
  {
    "media_type": "text",
    "content": "pengen tau deh 😌",
    "url": null,
    "timestamp": "2026-04-23T05:36:57.469000+00:00",
    "channel_id": "1484896114762317994"
  },
  {
    "media_type": "text",
    "content": "SEBERAPA BANYAK SIHH yang besok ketemu di percin 😌🫵",
    "url": null,
    "timestamp": "2026-04-23T05:36:58.911000+00:00",
    "channel_id": "1484896114762317994"
  },
  {
    "media_type": "text",
    "content": "SEBERAPAA BANYAK SIH yangg nungguin aku shonichi Ramune Team lovee ❤️❤️❤️",
    "url": null,
    "timestamp": "2026-04-23T05:37:00.328000+00:00",
    "channel_id": "1484896114762317994"
  },
  {
    "media_type": "text",
    "content": "SIAPA YANG KETEMUU AKUU LAGI HARI MINGGUU??",
    "url": null,
    "timestamp": "2026-04-23T05:37:01.718000+00:00",
    "channel_id": "1484896114762317994"
  },
  {
    "media_type": "image",
    "content": "",
    "url": "https://raw.githubusercontent.com/dmkr48/gen11/main/media/1484896114762317994/77fd56d8c6ef.jpg",
    "timestamp": "2026-04-23T11:24:48.198000+00:00",
    "channel_id": "1484896114762317994"
  },
  {
    "media_type": "image",
    "content": "",
    "url": "https://raw.githubusercontent.com/dmkr48/gen11/main/media/1484896114762317994/2430f5dd7b50.jpg",
    "timestamp": "2026-04-23T11:24:52.640000+00:00",
    "channel_id": "1484896114762317994"
  },
  {
    "media_type": "image",
    "content": "",
    "url": "https://raw.githubusercontent.com/dmkr48/gen11/main/media/1484896114762317994/e8d97ce1f5ff.jpg",
    "timestamp": "2026-04-23T11:25:00.683000+00:00",
    "channel_id": "1484896114762317994"
  },
  {
    "media_type": "image",
    "content": "",
    "url": "https://raw.githubusercontent.com/dmkr48/gen11/main/media/1484896114762317994/837151ec449f.jpg",
    "timestamp": "2026-04-23T11:25:04.904000+00:00",
    "channel_id": "1484896114762317994"
  },
  {
    "media_type": "image",
    "content": "",
    "url": "https://raw.githubusercontent.com/dmkr48/gen11/main/media/1484896114762317994/281301703e38.jpg",
    "timestamp": "2026-04-23T11:25:08.931000+00:00",
    "channel_id": "1484896114762317994"
  },
  {
    "media_type": "image",
    "content": "",
    "url": "https://raw.githubusercontent.com/dmkr48/gen11/main/media/1484896114762317994/a1040261a9af.jpg",
    "timestamp": "2026-04-23T11:25:13.413000+00:00",
    "channel_id": "1484896114762317994"
  },
  {
    "media_type": "image",
    "content": "",
    "url": "https://raw.githubusercontent.com/dmkr48/gen11/main/media/1484896114762317994/34632158271f.jpg",
    "timestamp": "2026-04-23T11:25:18.445000+00:00",
    "channel_id": "1484896114762317994"
  },
  {
    "media_type": "image",
    "content": "",
    "url": "https://raw.githubusercontent.com/dmkr48/gen11/main/media/1484896114762317994/f9b33e6fc78d.jpg",
    "timestamp": "2026-04-23T11:25:22.494000+00:00",
    "channel_id": "1484896114762317994"
  },
  {
    "media_type": "image",
    "content": "",
    "url": "https://raw.githubusercontent.com/dmkr48/gen11/main/media/1484896114762317994/78fbc56c4605.jpg",
    "timestamp": "2026-04-23T11:25:27.244000+00:00",
    "channel_id": "1484896114762317994"
  },
  {
    "media_type": "image",
    "content": "",
    "url": "https://raw.githubusercontent.com/dmkr48/gen11/main/media/1484896114762317994/ce99dc542d85.jpg",
    "timestamp": "2026-04-23T11:25:31.662000+00:00",
    "channel_id": "1484896114762317994"
  },
  {
    "media_type": "image",
    "content": "",
    "url": "https://raw.githubusercontent.com/dmkr48/gen11/main/media/1484896114762317994/e34988d36a8f.jpg",
    "timestamp": "2026-04-23T11:25:36.861000+00:00",
    "channel_id": "1484896114762317994"
  },
  {
    "media_type": "image",
    "content": "",
    "url": "https://raw.githubusercontent.com/dmkr48/gen11/main/media/1484896114762317994/4e84718d6554.jpg",
    "timestamp": "2026-04-23T11:25:41.825000+00:00",
    "channel_id": "1484896114762317994"
  },
  {
    "media_type": "image",
    "content": "",
    "url": "https://raw.githubusercontent.com/dmkr48/gen11/main/media/1484896114762317994/42428fe181d3.jpg",
    "timestamp": "2026-04-23T11:25:47.198000+00:00",
    "channel_id": "1484896114762317994"
  },
  {
    "media_type": "image",
    "content": "",
    "url": "https://raw.githubusercontent.com/dmkr48/gen11/main/media/1484896114762317994/7fb04ee0b81a.jpg",
    "timestamp": "2026-04-23T11:25:51.517000+00:00",
    "channel_id": "1484896114762317994"
  },
  {
    "media_type": "image",
    "content": "",
    "url": "https://raw.githubusercontent.com/dmkr48/gen11/main/media/1484896114762317994/b68fdd316c94.jpg",
    "timestamp": "2026-04-23T11:25:56.601000+00:00",
    "channel_id": "1484896114762317994"
  },
  {
    "media_type": "image",
    "content": "",
    "url": "https://raw.githubusercontent.com/dmkr48/gen11/main/media/1484896114762317994/83ae1ac813d9.jpg",
    "timestamp": "2026-04-23T11:26:00.904000+00:00",
    "channel_id": "1484896114762317994"
  },
  {
    "media_type": "image",
    "content": "",
    "url": "https://raw.githubusercontent.com/dmkr48/gen11/main/media/1484896114762317994/39f92c9aac15.jpg",
    "timestamp": "2026-04-23T11:26:04.715000+00:00",
    "channel_id": "1484896114762317994"
  },
  {
    "media_type": "image",
    "content": "",
    "url": "https://raw.githubusercontent.com/dmkr48/gen11/main/media/1484896114762317994/2032ee99031d.jpg",
    "timestamp": "2026-04-23T11:26:08.924000+00:00",
    "channel_id": "1484896114762317994"
  },
  {
    "media_type": "image",
    "content": "",
    "url": "https://raw.githubusercontent.com/dmkr48/gen11/main/media/1484896114762317994/98595e5266af.jpg",
    "timestamp": "2026-04-23T11:26:13.274000+00:00",
    "channel_id": "1484896114762317994"
  },
  {
    "media_type": "image",
    "content": "",
    "url": "https://raw.githubusercontent.com/dmkr48/gen11/main/media/1484896114762317994/476eb6462173.jpg",
    "timestamp": "2026-04-23T11:26:17.094000+00:00",
    "channel_id": "1484896114762317994"
  },
  {
    "media_type": "image",
    "content": "",
    "url": "https://raw.githubusercontent.com/dmkr48/gen11/main/media/1484896114762317994/e88e5eea1a08.jpg",
    "timestamp": "2026-04-23T11:26:21.040000+00:00",
    "channel_id": "1484896114762317994"
  },
  {
    "media_type": "image",
    "content": "",
    "url": "https://raw.githubusercontent.com/dmkr48/gen11/main/media/1484896114762317994/cc43d69d0004.jpg",
    "timestamp": "2026-04-23T11:26:30.535000+00:00",
    "channel_id": "1484896114762317994"
  },
  {
    "media_type": "image",
    "content": "",
    "url": "https://raw.githubusercontent.com/dmkr48/gen11/main/media/1484896114762317994/1b01f8055b7f.jpg",
    "timestamp": "2026-04-23T11:26:34.958000+00:00",
    "channel_id": "1484896114762317994"
  },
  {
    "media_type": "image",
    "content": "",
    "url": "https://raw.githubusercontent.com/dmkr48/gen11/main/media/1484896114762317994/c0dae1708eb0.jpg",
    "timestamp": "2026-04-23T11:26:39.935000+00:00",
    "channel_id": "1484896114762317994"
  },
  {
    "media_type": "image",
    "content": "",
    "url": "https://raw.githubusercontent.com/dmkr48/gen11/main/media/1484896114762317994/e054a7fc0863.jpg",
    "timestamp": "2026-04-23T11:26:43.825000+00:00",
    "channel_id": "1484896114762317994"
  },
  {
    "media_type": "image",
    "content": "",
    "url": "https://raw.githubusercontent.com/dmkr48/gen11/main/media/1484896114762317994/9d1e44988074.jpg",
    "timestamp": "2026-04-23T11:26:47.771000+00:00",
    "channel_id": "1484896114762317994"
  },
  {
    "media_type": "image",
    "content": "",
    "url": "https://raw.githubusercontent.com/dmkr48/gen11/main/media/1484896114762317994/516e3720d2c6.jpg",
    "timestamp": "2026-04-23T11:26:52.204000+00:00",
    "channel_id": "1484896114762317994"
  },
  {
    "media_type": "image",
    "content": "",
    "url": "https://raw.githubusercontent.com/dmkr48/gen11/main/media/1484896114762317994/754b0deacb52.jpg",
    "timestamp": "2026-04-23T11:26:56.581000+00:00",
    "channel_id": "1484896114762317994"
  },
  {
    "media_type": "image",
    "content": "",
    "url": "https://raw.githubusercontent.com/dmkr48/gen11/main/media/1484896114762317994/c1e5431488f1.jpg",
    "timestamp": "2026-04-23T11:27:01.397000+00:00",
    "channel_id": "1484896114762317994"
  },
  {
    "media_type": "image",
    "content": "",
    "url": "https://raw.githubusercontent.com/dmkr48/gen11/main/media/1484896114762317994/d874c4738b24.jpg",
    "timestamp": "2026-04-23T11:27:05.472000+00:00",
    "channel_id": "1484896114762317994"
  },
  {
    "media_type": "image",
    "content": "",
    "url": "https://raw.githubusercontent.com/dmkr48/gen11/main/media/1484896114762317994/266bfed3b97e.jpg",
    "timestamp": "2026-04-23T11:27:09.815000+00:00",
    "channel_id": "1484896114762317994"
  },
  {
    "media_type": "image",
    "content": "",
    "url": "https://raw.githubusercontent.com/dmkr48/gen11/main/media/1484896114762317994/3cecec682a9b.jpg",
    "timestamp": "2026-04-23T11:27:14.489000+00:00",
    "channel_id": "1484896114762317994"
  },
  {
    "media_type": "image",
    "content": "",
    "url": "https://raw.githubusercontent.com/dmkr48/gen11/main/media/1484896114762317994/70f1de5948a6.jpg",
    "timestamp": "2026-04-23T11:27:19.259000+00:00",
    "channel_id": "1484896114762317994"
  },
  {
    "media_type": "image",
    "content": "",
    "url": "https://raw.githubusercontent.com/dmkr48/gen11/main/media/1484896114762317994/7dc39b3e036c.jpg",
    "timestamp": "2026-04-23T11:27:24.005000+00:00",
    "channel_id": "1484896114762317994"
  },
  {
    "media_type": "image",
    "content": "",
    "url": "https://raw.githubusercontent.com/dmkr48/gen11/main/media/1484896114762317994/0c9a4c197f33.jpg",
    "timestamp": "2026-04-23T11:27:28.245000+00:00",
    "channel_id": "1484896114762317994"
  },
  {
    "media_type": "image",
    "content": "",
    "url": "https://raw.githubusercontent.com/dmkr48/gen11/main/media/1484896114762317994/e0b08c5a0209.jpg",
    "timestamp": "2026-04-23T11:27:32.103000+00:00",
    "channel_id": "1484896114762317994"
  },
  {
    "media_type": "image",
    "content": "",
    "url": "https://raw.githubusercontent.com/dmkr48/gen11/main/media/1484896114762317994/89831b1508f2.jpg",
    "timestamp": "2026-04-23T11:27:36.036000+00:00",
    "channel_id": "1484896114762317994"
  },
  {
    "media_type": "image",
    "content": "",
    "url": "https://raw.githubusercontent.com/dmkr48/gen11/main/media/1484896114762317994/33b865d6243b.jpg",
    "timestamp": "2026-04-23T11:27:39.932000+00:00",
    "channel_id": "1484896114762317994"
  },
  {
    "media_type": "image",
    "content": "",
    "url": "https://raw.githubusercontent.com/dmkr48/gen11/main/media/1484896114762317994/16f32eb94e53.jpg",
    "timestamp": "2026-04-23T11:27:43.872000+00:00",
    "channel_id": "1484896114762317994"
  },
  {
    "media_type": "image",
    "content": "",
    "url": "https://raw.githubusercontent.com/dmkr48/gen11/main/media/1484896114762317994/3c2aeb878762.jpg",
    "timestamp": "2026-04-23T11:27:47.748000+00:00",
    "channel_id": "1484896114762317994"
  },
  {
    "media_type": "image",
    "content": "SAPAA MAUUU MENCOBAA PEMPEK RASA KEJUUU😋😋😋",
    "url": "https://raw.githubusercontent.com/dmkr48/gen11/main/media/1484896114762317994/3a4e16ef066e.jpg",
    "timestamp": "2026-04-23T11:27:51.984000+00:00",
    "channel_id": "1484896114762317994"
  },
  {
    "media_type": "image",
    "content": "[photo]",
    "url": "https://raw.githubusercontent.com/dmkr48/gen11/main/media/1484896114762317994/ebdbb8b294c0.jpg",
    "timestamp": "2026-04-23T11:27:55.719000+00:00",
    "channel_id": "1484896114762317994"
  },
  {
    "media_type": "image",
    "content": "MAKAN SATE AYAM JUGA TADIII!!!",
    "url": "https://raw.githubusercontent.com/dmkr48/gen11/main/media/1484896114762317994/029f000053b9.jpg",
    "timestamp": "2026-04-23T11:27:59.715000+00:00",
    "channel_id": "1484896114762317994"
  },
  {
    "media_type": "text",
    "content": "kamu makan apaa?",
    "url": null,
    "timestamp": "2026-04-23T11:28:01.350000+00:00",
    "channel_id": "1484896114762317994"
  },
  {
    "media_type": "text",
    "content": "daripada perpisahan di jet coaster lebih baik aku menatapmu, sayonara…basah dalam hujan 🌧️",
    "url": null,
    "timestamp": "2026-04-23T11:28:02.771000+00:00",
    "channel_id": "1484896114762317994"
  },
  {
    "media_type": "text",
    "content": "ini rasanya bakal ditinggalin teman segenerasi :’(",
    "url": null,
    "timestamp": "2026-04-23T11:28:04.300000+00:00",
    "channel_id": "1484896114762317994"
  },
  {
    "media_type": "text",
    "content": "gatau sesedih ini…",
    "url": null,
    "timestamp": "2026-04-23T11:28:07.467000+00:00",
    "channel_id": "1484896114762317994"
  },
  {
    "media_type": "text",
    "content": "chel ilysm adik yg selalu ceria",
    "url": null,
    "timestamp": "2026-04-23T11:28:08.762000+00:00",
    "channel_id": "1484896114762317994"
  },
  {
    "media_type": "text",
    "content": "tolong jaga dan dukung chelsea yaah selama chelsea masih bareng sama kita, dukung juga buat studinya untuk anak kecil yang lagi tumbuh dewasa itu 😔",
    "url": null,
    "timestamp": "2026-04-23T11:28:10.265000+00:00",
    "channel_id": "1484896114762317994"
  },
  {
    "media_type": "video",
    "content": "VIDEOOO PERTAMAA DIII PM AKUUU!",
    "url": "https://raw.githubusercontent.com/dmkr48/gen11/main/media/1484896114762317994/b2f9072548db.mp4",
    "timestamp": "2026-04-23T11:28:13.763000+00:00",
    "channel_id": "1484896114762317994"
  },
  {
    "media_type": "text",
    "content": "ini pas aku selesai tour dan dikasih tour guidenya gelang!! soo sweet of herr 🥺🥺",
    "url": null,
    "timestamp": "2026-04-23T11:28:15.335000+00:00",
    "channel_id": "1484896114762317994"
  },
  {
    "media_type": "image",
    "content": "ingettt gak love letter ini??",
    "url": "https://raw.githubusercontent.com/dmkr48/gen11/main/media/1484896114762317994/78c17e27d44f.jpg",
    "timestamp": "2026-04-23T11:28:21.896000+00:00",
    "channel_id": "1484896114762317994"
  },
  {
    "media_type": "text",
    "content": "siapa yang dapett??",
    "url": null,
    "timestamp": "2026-04-23T11:28:23.988000+00:00",
    "channel_id": "1484896114762317994"
  },
  {
    "media_type": "text",
    "content": "di semua letternya aku gambar fox karena fox eye aku hihihi 🦊",
    "url": null,
    "timestamp": "2026-04-23T11:28:25.334000+00:00",
    "channel_id": "1484896114762317994"
  },
  {
    "media_type": "text",
    "content": "menurut kamu seberapa fox akuu?? 😼",
    "url": null,
    "timestamp": "2026-04-23T11:28:26.895000+00:00",
    "channel_id": "1484896114762317994"
  },
  {
    "media_type": "text",
    "content": "gimanaa hari jumatnyaa?",
    "url": null,
    "timestamp": "2026-04-23T11:28:28.286000+00:00",
    "channel_id": "1484896114762317994"
  },
  {
    "media_type": "text",
    "content": "ASIK KAHH? libur juga kan kamu!",
    "url": null,
    "timestamp": "2026-04-23T11:28:29.603000+00:00",
    "channel_id": "1484896114762317994"
  },
  {
    "media_type": "text",
    "content": "TAU GAK SIH",
    "url": null,
    "timestamp": "2026-04-23T11:28:31.063000+00:00",
    "channel_id": "1484896114762317994"
  },
  {
    "media_type": "text",
    "content": "aku hari inii full istirahat hihihi",
    "url": null,
    "timestamp": "2026-04-23T11:28:32.569000+00:00",
    "channel_id": "1484896114762317994"
  },
  {
    "media_type": "text",
    "content": "KALO BERKEGIATAN SAMA TIM LOVE RASANYA PADA SEMANGAT BANGET KAN ANAKANAKNYA!!!",
    "url": null,
    "timestamp": "2026-04-23T11:28:34.005000+00:00",
    "channel_id": "1484896114762317994"
  },
  {
    "media_type": "text",
    "content": "aku sampe berpikir gini",
    "url": null,
    "timestamp": "2026-04-23T11:28:35.344000+00:00",
    "channel_id": "1484896114762317994"
  },
  {
    "media_type": "text",
    "content": "gapapa walaupun udah tua masih harus semangat KWKWK",
    "url": null,
    "timestamp": "2026-04-23T11:28:36.858000+00:00",
    "channel_id": "1484896114762317994"
  },
  {
    "media_type": "text",
    "content": "kita wujudka semangat tua itu 💪💪😌",
    "url": null,
    "timestamp": "2026-04-23T11:28:38.274000+00:00",
    "channel_id": "1484896114762317994"
  },
  {
    "media_type": "text",
    "content": "ya aku juga tau umur kalian lebih deket ke aku daripada ke mereka jadi semoga kamu tetep semangat jugaa!",
    "url": null,
    "timestamp": "2026-04-23T11:29:03.353000+00:00",
    "channel_id": "1484896114762317994"
  },
  {
    "media_type": "text",
    "content": "seru banget deh 🤩‼️",
    "url": null,
    "timestamp": "2026-04-23T11:29:04.763000+00:00",
    "channel_id": "1484896114762317994"
  },
  {
    "media_type": "text",
    "content": "ga sabar show bareng team love!",
    "url": null,
    "timestamp": "2026-04-23T11:29:06.126000+00:00",
    "channel_id": "1484896114762317994"
  },
  {
    "media_type": "text",
    "content": "kata cepio kita kayak punya dunia sendiri tapi fans gatau HAHAHA",
    "url": null,
    "timestamp": "2026-04-23T11:29:07.526000+00:00",
    "channel_id": "1484896114762317994"
  },
  {
    "media_type": "text",
    "content": "tunggu kita shonichi yaa!! 😼🫰",
    "url": null,
    "timestamp": "2026-04-23T11:29:08.912000+00:00",
    "channel_id": "1484896114762317994"
  },
  {
    "media_type": "image",
    "content": "tadii otw teater",
    "url": "https://raw.githubusercontent.com/dmkr48/gen11/main/media/1484896114762317994/7f0c881b445b.jpg",
    "timestamp": "2026-04-23T11:29:12.677000+00:00",
    "channel_id": "1484896114762317994"
  },
  {
    "media_type": "image",
    "content": "thanks untuk percin hari ini!!",
    "url": "https://raw.githubusercontent.com/dmkr48/gen11/main/media/1484896114762317994/90cd6e2ed37d.jpg",
    "timestamp": "2026-04-23T11:29:16.229000+00:00",
    "channel_id": "1484896114762317994"
  },
  {
    "media_type": "image",
    "content": "[photo]",
    "url": "https://raw.githubusercontent.com/dmkr48/gen11/main/media/1484896114762317994/bbe69e119364.jpg",
    "timestamp": "2026-04-23T11:29:20.740000+00:00",
    "channel_id": "1484896114762317994"
  },
  {
    "media_type": "image",
    "content": "[photo]",
    "url": "https://raw.githubusercontent.com/dmkr48/gen11/main/media/1484896114762317994/7c97006fd115.jpg",
    "timestamp": "2026-04-23T11:29:24.527000+00:00",
    "channel_id": "1484896114762317994"
  },
  {
    "media_type": "image",
    "content": "[photo]",
    "url": "https://raw.githubusercontent.com/dmkr48/gen11/main/media/1484896114762317994/9dc8939b2cbc.jpg",
    "timestamp": "2026-04-23T11:29:28.210000+00:00",
    "channel_id": "1484896114762317994"
  },
  {
    "media_type": "text",
    "content": "SERU DEH HR INI",
    "url": null,
    "timestamp": "2026-04-23T11:29:29.737000+00:00",
    "channel_id": "1484896114762317994"
  },
  {
    "media_type": "text",
    "content": "makasi yang tadi sudah datang maupun nonton di live streaming",
    "url": null,
    "timestamp": "2026-04-23T11:29:31.151000+00:00",
    "channel_id": "1484896114762317994"
  },
  {
    "media_type": "text",
    "content": "",
    "url": null,
    "timestamp": "2026-04-23T11:29:32.659000+00:00",
    "channel_id": "1484896114762317994"
  },
  {
    "media_type": "text",
    "content": "HAIII!",
    "url": null,
    "timestamp": "2026-04-23T11:29:34.085000+00:00",
    "channel_id": "1484896114762317994"
  },
  {
    "media_type": "text",
    "content": "aku seharian mikirin kalian 🥹",
    "url": null,
    "timestamp": "2026-04-23T11:29:35.479000+00:00",
    "channel_id": "1484896114762317994"
  },
  {
    "media_type": "text",
    "content": "Makasih ya poster #cynthiasangpianis hujan 🎹☔️",
    "url": null,
    "timestamp": "2026-04-23T11:29:36.918000+00:00",
    "channel_id": "1484896114762317994"
  },
  {
    "media_type": "text",
    "content": "aku pengen lebih berjuang lagi sama kalian kali iniii! yuk kita bareng-bareng berusaha untuk ituu!",
    "url": null,
    "timestamp": "2026-04-23T11:29:38.230000+00:00",
    "channel_id": "1484896114762317994"
  },
  {
    "media_type": "image",
    "content": "SUSHIIII! a treat for me myself and i 🫶😌",
    "url": "https://raw.githubusercontent.com/dmkr48/gen11/main/media/1484896114762317994/48ccf0fcfdf5.jpg",
    "timestamp": "2026-04-23T11:29:42.084000+00:00",
    "channel_id": "1484896114762317994"
  },
  {
    "media_type": "image",
    "content": "butter tteok yang lagi virall! tau gak sih??",
    "url": "https://raw.githubusercontent.com/dmkr48/gen11/main/media/1484896114762317994/1899cb6fe45e.jpg",
    "timestamp": "2026-04-23T11:29:46.173000+00:00",
    "channel_id": "1484896114762317994"
  },
  {
    "media_type": "image",
    "content": "ESPRESSO MATCHA LATTE SATU YA KAK! Tandatanda kedewasaan seorang wanita, minumnya tidak ice chocolate lagi 😌🫰",
    "url": "https://raw.githubusercontent.com/dmkr48/gen11/main/media/1484896114762317994/481d18f375d7.jpg",
    "timestamp": "2026-04-23T11:29:49.637000+00:00",
    "channel_id": "1484896114762317994"
  },
  {
    "media_type": "image",
    "content": "ini adalah keychain yang luculucu banget yaampun sanrio semua, coba tebak mana yang aku beli???! super duper cute",
    "url": "https://raw.githubusercontent.com/dmkr48/gen11/main/media/1484896114762317994/e90ba756a396.jpg",
    "timestamp": "2026-04-23T11:30:07.870000+00:00",
    "channel_id": "1484896114762317994"
  },
  {
    "media_type": "image",
    "content": "almost bought this necklace tapi belom beli, aku galau bcs its pretty tapi aku gatau bakal aku pakai atau tidak kalau aku beli aku takut aku hanya lapar mata dan aku takut hanya impulsif semata",
    "url": "https://raw.githubusercontent.com/dmkr48/gen11/main/media/1484896114762317994/5947cfe81a87.jpg",
    "timestamp": "2026-04-23T11:30:11.286000+00:00",
    "channel_id": "1484896114762317994"
  },
  {
    "media_type": "image",
    "content": "okai ini juga dress! tau banget kan aku jadi suka dresssdress gitu! coba tebak aku beli yang mana??! this is a preparation untuk know more tentang girly things, kamu akan belajar suatu saat nanti ‼️😌",
    "url": "https://raw.githubusercontent.com/dmkr48/gen11/main/media/1484896114762317994/e0d56eb4eb02.jpg",
    "timestamp": "2026-04-23T11:30:15.746000+00:00",
    "channel_id": "1484896114762317994"
  },
  {
    "media_type": "text",
    "content": "hai!!",
    "url": null,
    "timestamp": "2026-04-23T11:30:17.247000+00:00",
    "channel_id": "1484896114762317994"
  },
  {
    "media_type": "text",
    "content": "gimana hari inii??",
    "url": null,
    "timestamp": "2026-04-23T11:30:18.668000+00:00",
    "channel_id": "1484896114762317994"
  },
  {
    "media_type": "text",
    "content": "udah ngapain ajaa?",
    "url": null,
    "timestamp": "2026-04-23T11:30:20.218000+00:00",
    "channel_id": "1484896114762317994"
  },
  {
    "media_type": "image",
    "content": "[photo]",
    "url": "https://raw.githubusercontent.com/dmkr48/gen11/main/media/1484896114762317994/4df04488f7bc.jpg",
    "timestamp": "2026-04-23T11:30:23.664000+00:00",
    "channel_id": "1484896114762317994"
  },
  {
    "media_type": "image",
    "content": "[photo]",
    "url": "https://raw.githubusercontent.com/dmkr48/gen11/main/media/1484896114762317994/037195f6ad3e.jpg",
    "timestamp": "2026-04-23T11:30:27.361000+00:00",
    "channel_id": "1484896114762317994"
  },
  {
    "media_type": "image",
    "content": "[photo]",
    "url": "https://raw.githubusercontent.com/dmkr48/gen11/main/media/1484896114762317994/36a1eff01adc.jpg",
    "timestamp": "2026-04-23T11:30:31.198000+00:00",
    "channel_id": "1484896114762317994"
  },
  {
    "media_type": "image",
    "content": "[photo]",
    "url": "https://raw.githubusercontent.com/dmkr48/gen11/main/media/1484896114762317994/6f9e71f8c39c.jpg",
    "timestamp": "2026-04-23T11:30:34.631000+00:00",
    "channel_id": "1484896114762317994"
  },
  {
    "media_type": "image",
    "content": "[photo]",
    "url": "https://raw.githubusercontent.com/dmkr48/gen11/main/media/1484896114762317994/f312548139d2.jpg",
    "timestamp": "2026-04-23T11:30:38.611000+00:00",
    "channel_id": "1484896114762317994"
  },
  {
    "media_type": "image",
    "content": "[photo]",
    "url": "https://raw.githubusercontent.com/dmkr48/gen11/main/media/1484896114762317994/ed81f160682b.jpg",
    "timestamp": "2026-04-23T11:30:42.040000+00:00",
    "channel_id": "1484896114762317994"
  },
  {
    "media_type": "image",
    "content": "[photo]",
    "url": "https://raw.githubusercontent.com/dmkr48/gen11/main/media/1484896114762317994/5c98fa6255b3.jpg",
    "timestamp": "2026-04-23T11:30:45.231000+00:00",
    "channel_id": "1484896114762317994"
  },
  {
    "media_type": "image",
    "content": "[photo]",
    "url": "https://raw.githubusercontent.com/dmkr48/gen11/main/media/1484896114762317994/a8a390251cd2.jpg",
    "timestamp": "2026-04-23T11:30:49.461000+00:00",
    "channel_id": "1484896114762317994"
  },
  {
    "media_type": "image",
    "content": "[photo]",
    "url": "https://raw.githubusercontent.com/dmkr48/gen11/main/media/1484896114762317994/6e2dd77114fe.jpg",
    "timestamp": "2026-04-23T11:30:53.119000+00:00",
    "channel_id": "1484896114762317994"
  },
  {
    "media_type": "image",
    "content": "HMM benefit PM kah ini? 😝😝",
    "url": "https://raw.githubusercontent.com/dmkr48/gen11/main/media/1484896114762317994/a9fd490e3137.jpg",
    "timestamp": "2026-04-23T11:30:56.625000+00:00",
    "channel_id": "1484896114762317994"
  },
  {
    "media_type": "image",
    "content": "ini aku post di IG",
    "url": "https://raw.githubusercontent.com/dmkr48/gen11/main/media/1484896114762317994/6aaa59a5af87.jpg",
    "timestamp": "2026-04-23T11:31:00.117000+00:00",
    "channel_id": "1484896114762317994"
  },
  {
    "media_type": "image",
    "content": "[photo]",
    "url": "https://raw.githubusercontent.com/dmkr48/gen11/main/media/1484896114762317994/c7686fc08875.jpg",
    "timestamp": "2026-04-23T11:31:03.781000+00:00",
    "channel_id": "1484896114762317994"
  },
  {
    "media_type": "image",
    "content": "[photo]",
    "url": "https://raw.githubusercontent.com/dmkr48/gen11/main/media/1484896114762317994/c7034be4f327.jpg",
    "timestamp": "2026-04-23T11:31:07.261000+00:00",
    "channel_id": "1484896114762317994"
  },
  {
    "media_type": "text",
    "content": "tapi grid 9",
    "url": null,
    "timestamp": "2026-04-23T11:31:08.754000+00:00",
    "channel_id": "1484896114762317994"
  },
  {
    "media_type": "text",
    "content": "atau lebih yeah",
    "url": null,
    "timestamp": "2026-04-23T11:31:10.227000+00:00",
    "channel_id": "1484896114762317994"
  },
  {
    "media_type": "text",
    "content": "tapi ini aku post satusatu disini",
    "url": null,
    "timestamp": "2026-04-23T11:31:11.622000+00:00",
    "channel_id": "1484896114762317994"
  },
  {
    "media_type": "text",
    "content": "aku lagi suka banget nonton kartun tau KWWK",
    "url": null,
    "timestamp": "2026-04-23T11:31:12.973000+00:00",
    "channel_id": "1484896114762317994"
  },
  {
    "media_type": "text",
    "content": "movies or series yang animasinya bagus 🥺🥺🥺",
    "url": null,
    "timestamp": "2026-04-23T11:31:14.371000+00:00",
    "channel_id": "1484896114762317994"
  },
  {
    "media_type": "text",
    "content": "suka bgtt",
    "url": null,
    "timestamp": "2026-04-23T11:31:15.746000+00:00",
    "channel_id": "1484896114762317994"
  },
  {
    "media_type": "text",
    "content": "aku hari ini mimpi tentang jalanjalan lagi",
    "url": null,
    "timestamp": "2026-04-23T11:31:17.025000+00:00",
    "channel_id": "1484896114762317994"
  },
  {
    "media_type": "text",
    "content": "udah 3 hari aku mimpi tentang jalanjalan",
    "url": null,
    "timestamp": "2026-04-23T11:31:18.340000+00:00",
    "channel_id": "1484896114762317994"
  },
  {
    "media_type": "text",
    "content": "pertanda apa yah ini??",
    "url": null,
    "timestamp": "2026-04-23T11:31:19.769000+00:00",
    "channel_id": "1484896114762317994"
  },
  {
    "media_type": "text",
    "content": "hiii",
    "url": null,
    "timestamp": "2026-04-23T11:31:21.247000+00:00",
    "channel_id": "1484896114762317994"
  },
  {
    "media_type": "text",
    "content": "beneran pengen nobar bola deh WKWK",
    "url": null,
    "timestamp": "2026-04-23T11:31:22.732000+00:00",
    "channel_id": "1484896114762317994"
  },
  {
    "media_type": "text",
    "content": "GUIDE AKU SMPE AKU MENEMUKAN TIM BOLA FAVORIT",
    "url": null,
    "timestamp": "2026-04-23T11:31:24.182000+00:00",
    "channel_id": "1484896114762317994"
  },
  {
    "media_type": "text",
    "content": "mumpung aku blum terjun trlalu dalam nih",
    "url": null,
    "timestamp": "2026-04-23T11:31:25.737000+00:00",
    "channel_id": "1484896114762317994"
  },
  {
    "media_type": "text",
    "content": "klo nanti udah punya pilihanku sendiri udah gabisa diganggu gugat 😌",
    "url": null,
    "timestamp": "2026-04-23T11:31:27.376000+00:00",
    "channel_id": "1484896114762317994"
  },
  {
    "media_type": "text",
    "content": "tadi makan salad buah",
    "url": null,
    "timestamp": "2026-04-23T11:31:28.744000+00:00",
    "channel_id": "1484896114762317994"
  },
  {
    "media_type": "text",
    "content": "sekalisekali makan sehat walau ga selalu juga 😁😁😁",
    "url": null,
    "timestamp": "2026-04-23T11:31:30.363000+00:00",
    "channel_id": "1484896114762317994"
  },
  {
    "media_type": "text",
    "content": "WETSSS makasih yaa nobarnya",
    "url": null,
    "timestamp": "2026-04-23T11:31:31.777000+00:00",
    "channel_id": "1484896114762317994"
  },
  {
    "media_type": "text",
    "content": "hari ini emang harinya 2-0 gini ya",
    "url": null,
    "timestamp": "2026-04-23T11:31:33.283000+00:00",
    "channel_id": "1484896114762317994"
  },
  {
    "media_type": "text",
    "content": "WKWKWKW bolak balik match sama aja gini harganya",
    "url": null,
    "timestamp": "2026-04-23T11:31:34.654000+00:00",
    "channel_id": "1484896114762317994"
  },
  {
    "media_type": "text",
    "content": "HASILNYA",
    "url": null,
    "timestamp": "2026-04-23T11:32:07.641000+00:00",
    "channel_id": "1484896114762317994"
  },
  {
    "media_type": "text",
    "content": "kok jadi harganya KWKWK",
    "url": null,
    "timestamp": "2026-04-23T11:32:09.057000+00:00",
    "channel_id": "1484896114762317994"
  },
  {
    "media_type": "text",
    "content": "sedang dalam misi mengenali pemain”nya KWKWKW",
    "url": null,
    "timestamp": "2026-04-23T11:32:10.565000+00:00",
    "channel_id": "1484896114762317994"
  },
  {
    "media_type": "text",
    "content": "kemarin sudah didoktrin sedikit pemain” andalannya",
    "url": null,
    "timestamp": "2026-04-23T11:32:11.939000+00:00",
    "channel_id": "1484896114762317994"
  },
  {
    "media_type": "text",
    "content": "MANTAP NOBAR BERIKUTNYA HARI SABTU DEH YUK WKWKW",
    "url": null,
    "timestamp": "2026-04-23T11:32:13.381000+00:00",
    "channel_id": "1484896114762317994"
  },
  {
    "media_type": "text",
    "content": "habisss makann saltbread!",
    "url": null,
    "timestamp": "2026-04-23T11:32:15.012000+00:00",
    "channel_id": "1484896114762317994"
  },
  {
    "media_type": "text",
    "content": "dari kemarin ngobrolin saltbread terus sama cepio 🥹",
    "url": null,
    "timestamp": "2026-04-23T11:32:16.331000+00:00",
    "channel_id": "1484896114762317994"
  },
  {
    "media_type": "text",
    "content": "jadi tadi aku pesen aja ke rumah",
    "url": null,
    "timestamp": "2026-04-23T11:32:17.815000+00:00",
    "channel_id": "1484896114762317994"
  },
  {
    "media_type": "text",
    "content": "salah satu jajanan viral yang emang enak menurutku 🫰",
    "url": null,
    "timestamp": "2026-04-23T11:32:19.179000+00:00",
    "channel_id": "1484896114762317994"
  },
  {
    "media_type": "text",
    "content": "habis makan salad buah lagi!!",
    "url": null,
    "timestamp": "2026-04-23T11:32:20.592000+00:00",
    "channel_id": "1484896114762317994"
  },
  {
    "media_type": "text",
    "content": "kemarin porsi kecil",
    "url": null,
    "timestamp": "2026-04-23T11:32:22.001000+00:00",
    "channel_id": "1484896114762317994"
  },
  {
    "media_type": "text",
    "content": "hari ini makan yang porsi besar",
    "url": null,
    "timestamp": "2026-04-23T11:32:23.365000+00:00",
    "channel_id": "1484896114762317994"
  },
  {
    "media_type": "text",
    "content": "ituuuu what i eat in today! salad buah dan salt bread",
    "url": null,
    "timestamp": "2026-04-23T11:32:24.724000+00:00",
    "channel_id": "1484896114762317994"
  },
  {
    "media_type": "text",
    "content": "lagi mengurangi nasi 🍚",
    "url": null,
    "timestamp": "2026-04-23T11:32:26.099000+00:00",
    "channel_id": "1484896114762317994"
  },
  {
    "media_type": "text",
    "content": "tapi biasa malah makan kalau habis latihan HAAHHA",
    "url": null,
    "timestamp": "2026-04-23T11:32:27.460000+00:00",
    "channel_id": "1484896114762317994"
  },
  {
    "media_type": "text",
    "content": "btw kalau nanti aku sampai rumah tidak terlalu malam aku mauu livee!",
    "url": null,
    "timestamp": "2026-04-23T11:32:28.898000+00:00",
    "channel_id": "1484896114762317994"
  },
  {
    "media_type": "text",
    "content": "sdh lama tidak ngobrol (selain nobar) WKWKW",
    "url": null,
    "timestamp": "2026-04-23T11:32:30.363000+00:00",
    "channel_id": "1484896114762317994"
  },
  {
    "media_type": "video",
    "content": "[video]",
    "url": "https://raw.githubusercontent.com/dmkr48/gen11/main/media/1484896114762317994/94511e886118.mp4",
    "timestamp": "2026-04-23T11:32:33.960000+00:00",
    "channel_id": "1484896114762317994"
  },
  {
    "media_type": "text",
    "content": "heloo! lagi apa??",
    "url": null,
    "timestamp": "2026-04-23T11:32:35.583000+00:00",
    "channel_id": "1484896114762317994"
  },
  {
    "media_type": "text",
    "content": "udah pulang kegiatan kahh??",
    "url": null,
    "timestamp": "2026-04-23T11:32:36.962000+00:00",
    "channel_id": "1484896114762317994"
  },
  {
    "media_type": "text",
    "content": "jangan lupa senyum jangan lupa bahagia jangan lupa #cynabungg 😜😜",
    "url": null,
    "timestamp": "2026-04-23T11:33:08.810000+00:00",
    "channel_id": "1484896114762317994"
  },
  {
    "media_type": "text",
    "content": "akuuuuu senang hari ini sampai rumah dan bisa istirahat di rumah LAGIIII",
    "url": null,
    "timestamp": "2026-04-23T11:33:10.214000+00:00",
    "channel_id": "1484896114762317994"
  },
  {
    "media_type": "text",
    "content": "jangan lupa bersyukur teman",
    "url": null,
    "timestamp": "2026-04-23T11:33:11.585000+00:00",
    "channel_id": "1484896114762317994"
  },
  {
    "media_type": "text",
    "content": "tadi siang makannn sandwich bread",
    "url": null,
    "timestamp": "2026-04-23T11:33:13.126000+00:00",
    "channel_id": "1484896114762317994"
  },
  {
    "media_type": "text",
    "content": "sehat lagiii",
    "url": null,
    "timestamp": "2026-04-23T11:33:14.756000+00:00",
    "channel_id": "1484896114762317994"
  },
  {
    "media_type": "text",
    "content": "selangkah menuju cynthia lebih sehat",
    "url": null,
    "timestamp": "2026-04-23T11:33:16.169000+00:00",
    "channel_id": "1484896114762317994"
  },
  {
    "media_type": "video",
    "content": "jadi pengen makan curry lagiiii",
    "url": "https://raw.githubusercontent.com/dmkr48/gen11/main/media/1484896114762317994/9ea959a305c5.mp4",
    "timestamp": "2026-04-23T11:33:19.947000+00:00",
    "channel_id": "1484896114762317994"
  },
  {
    "media_type": "text",
    "content": "bagaimanaaaa hari jumatnya? semoga berjalan lancar ya kemarinnnn! kalaupun ada yang bikin tidak enak gapapa! kalau ada hal yang mengganjal diluapkan saja! semoga usah kamu setiap harinya akan berbuah di kemudian hari! jangan pernah menyerah apapun yang terjadi ya ☺️🫰 ada aku",
    "url": null,
    "timestamp": "2026-04-23T11:33:21.807000+00:00",
    "channel_id": "1484896114762317994"
  },
  {
    "media_type": "text",
    "content": "dan aku juga ada kalian jadi aku ga akan pernah menyerah ☺️",
    "url": null,
    "timestamp": "2026-04-23T11:33:23.237000+00:00",
    "channel_id": "1484896114762317994"
  },
  {
    "media_type": "image",
    "content": "seneng banget tampil lagi di GOR! jujur kalao tampil untuk acara pertandingan gitu terbawa semangat pertandingannya juga! apalagi kemaren bulu tangkisss! olahraga yang acu suka! SEMANGAT OLAHRAGA AKU LAGI MEMBARA LOH INI 200% 🔥☄️🏸",
    "url": "https://raw.githubusercontent.com/dmkr48/gen11/main/media/1484896114762317994/8f87c297a8ad.jpg",
    "timestamp": "2026-04-23T11:33:27.023000+00:00",
    "channel_id": "1484896114762317994"
  },
  {
    "media_type": "image",
    "content": "HIHI TERLIHAT BERBEDA GA",
    "url": "https://raw.githubusercontent.com/dmkr48/gen11/main/media/1484896114762317994/b6879b773943.jpg",
    "timestamp": "2026-04-23T11:33:31.279000+00:00",
    "channel_id": "1484896114762317994"
  },
  {
    "media_type": "image",
    "content": "foto foto di backstage yang belum terspill",
    "url": "https://raw.githubusercontent.com/dmkr48/gen11/main/media/1484896114762317994/950c89260173.jpg",
    "timestamp": "2026-04-23T11:33:34.938000+00:00",
    "channel_id": "1484896114762317994"
  },
  {
    "media_type": "image",
    "content": "UDAH KANGEN LAGII DEH! COBA REPLY YANG UDAH KANGEN 🥺🫰🫰",
    "url": "https://raw.githubusercontent.com/dmkr48/gen11/main/media/1484896114762317994/b0e02644a842.jpg",
    "timestamp": "2026-04-23T11:33:39.337000+00:00",
    "channel_id": "1484896114762317994"
  },
  {
    "media_type": "image",
    "content": "aku merasa hairstyle aku bocil banget karena tampilnya bareng dedek dedek jadi harus stay younggg",
    "url": "https://raw.githubusercontent.com/dmkr48/gen11/main/media/1484896114762317994/a5db4da26c7a.jpg",
    "timestamp": "2026-04-23T11:33:43.546000+00:00",
    "channel_id": "1484896114762317994"
  },
  {
    "media_type": "image",
    "content": "BLUSHING PIPI AKU KETEMU KAMU 🥰",
    "url": "https://raw.githubusercontent.com/dmkr48/gen11/main/media/1484896114762317994/66a8db1035c4.jpg",
    "timestamp": "2026-04-23T11:33:48.107000+00:00",
    "channel_id": "1484896114762317994"
  },
  {
    "media_type": "text",
    "content": "akuuu hari iniii nontonn ulang tahunnya elinn!!",
    "url": null,
    "timestamp": "2026-04-23T11:33:49.760000+00:00",
    "channel_id": "1484896114762317994"
  },
  {
    "media_type": "text",
    "content": "gimana kalian yang nonton ramune pertama dari team love?? senenggg gaaaa? 🥰🫰",
    "url": null,
    "timestamp": "2026-04-23T11:33:51.163000+00:00",
    "channel_id": "1484896114762317994"
  },
  {
    "media_type": "text",
    "content": "tunggu aku di ramune team love juga yah‼️",
    "url": null,
    "timestamp": "2026-04-23T11:33:52.430000+00:00",
    "channel_id": "1484896114762317994"
  },
  {
    "media_type": "image",
    "content": "tadi beli saltbread di fx",
    "url": "https://raw.githubusercontent.com/dmkr48/gen11/main/media/1484896114762317994/3253e28e0e52.jpg",
    "timestamp": "2026-04-23T11:33:56.611000+00:00",
    "channel_id": "1484896114762317994"
  },
  {
    "media_type": "text",
    "content": "jujur kecintaan aku akan saltbread makin bertambah",
    "url": null,
    "timestamp": "2026-04-23T11:33:58.151000+00:00",
    "channel_id": "1484896114762317994"
  },
  {
    "media_type": "text",
    "content": "kalo ditanya jadi mau ga bawain manazashi? mau dong mau BANGET 🥹🥹🥹🫰🫰",
    "url": null,
    "timestamp": "2026-04-23T11:34:10.949000+00:00",
    "channel_id": "1484896114762317994"
  },
  {
    "media_type": "text",
    "content": "makanya langsung aja sini mana #cynabung",
    "url": null,
    "timestamp": "2026-04-23T11:34:12.302000+00:00",
    "channel_id": "1484896114762317994"
  },
  {
    "media_type": "text",
    "content": "siap menjadi",
    "url": null,
    "timestamp": "2026-04-23T11:34:13.768000+00:00",
    "channel_id": "1484896114762317994"
  },
  {
    "media_type": "text",
    "content": "DOOONAATTTT 🍩",
    "url": null,
    "timestamp": "2026-04-23T11:34:15.445000+00:00",
    "channel_id": "1484896114762317994"
  },
  {
    "media_type": "audio",
    "content": "[voice note]",
    "url": "https://raw.githubusercontent.com/dmkr48/gen11/main/media/1484896114762317994/27632860753d.m4a",
    "timestamp": "2026-04-23T11:34:17.884000+00:00",
    "channel_id": "1484896114762317994"
  },
  {
    "media_type": "audio",
    "content": "[voice note]",
    "url": "https://raw.githubusercontent.com/dmkr48/gen11/main/media/1484896114762317994/f7918a8d2984.m4a",
    "timestamp": "2026-04-23T11:34:20.788000+00:00",
    "channel_id": "1484896114762317994"
  },
  {
    "media_type": "audio",
    "content": "[voice note]",
    "url": "https://raw.githubusercontent.com/dmkr48/gen11/main/media/1484896114762317994/b6cb2c803736.m4a",
    "timestamp": "2026-04-23T11:34:23.941000+00:00",
    "channel_id": "1484896114762317994"
  },
  {
    "media_type": "text",
    "content": "lebih dari ini… kan menambah kesedihan 🥲",
    "url": null,
    "timestamp": "2026-04-23T11:34:25.460000+00:00",
    "channel_id": "1484896114762317994"
  },
  {
    "media_type": "text",
    "content": "tadi nonton sts elin jadi inget sts kita bersama deh 👉🏻👈🏻",
    "url": null,
    "timestamp": "2026-04-23T11:34:26.828000+00:00",
    "channel_id": "1484896114762317994"
  },
  {
    "media_type": "image",
    "content": "ksygnku duniaku 🥹",
    "url": "https://raw.githubusercontent.com/dmkr48/gen11/main/media/1484896114762317994/e2b5797440cc.jpg",
    "timestamp": "2026-04-23T11:34:30.212000+00:00",
    "channel_id": "1484896114762317994"
  },
  {
    "media_type": "text",
    "content": "haiii",
    "url": null,
    "timestamp": "2026-04-23T11:34:32.010000+00:00",
    "channel_id": "1484896114762317994"
  },
  {
    "media_type": "text",
    "content": "MAUU NGAPAINNN AJA HARI INIII??",
    "url": null,
    "timestamp": "2026-04-23T11:34:33.280000+00:00",
    "channel_id": "1484896114762317994"
  },
  {
    "media_type": "image",
    "content": "[photo]",
    "url": "https://raw.githubusercontent.com/dmkr48/gen11/main/media/1484896114762317994/aedfb1730e03.jpg",
    "timestamp": "2026-04-23T11:34:36.881000+00:00",
    "channel_id": "1484896114762317994"
  },
  {
    "media_type": "image",
    "content": "[photo]",
    "url": "https://raw.githubusercontent.com/dmkr48/gen11/main/media/1484896114762317994/f3fb5195058e.jpg",
    "timestamp": "2026-04-23T11:34:40.867000+00:00",
    "channel_id": "1484896114762317994"
  },
  {
    "media_type": "image",
    "content": "[photo]",
    "url": "https://raw.githubusercontent.com/dmkr48/gen11/main/media/1484896114762317994/cbf86a5cbd95.jpg",
    "timestamp": "2026-04-23T11:34:44.810000+00:00",
    "channel_id": "1484896114762317994"
  },
  {
    "media_type": "image",
    "content": "semalam",
    "url": "https://raw.githubusercontent.com/dmkr48/gen11/main/media/1484896114762317994/fef8bb93ce9f.jpg",
    "timestamp": "2026-04-23T11:34:48.165000+00:00",
    "channel_id": "1484896114762317994"
  },
  {
    "media_type": "text",
    "content": "heyyy!",
    "url": null,
    "timestamp": "2026-04-23T11:34:49.807000+00:00",
    "channel_id": "1484896114762317994"
  },
  {
    "media_type": "text",
    "content": "makasih ya vcnyaaa",
    "url": null,
    "timestamp": "2026-04-23T11:34:51.221000+00:00",
    "channel_id": "1484896114762317994"
  },
  {
    "media_type": "text",
    "content": "yang tadi bertemu",
    "url": null,
    "timestamp": "2026-04-23T11:34:52.619000+00:00",
    "channel_id": "1484896114762317994"
  },
  {
    "media_type": "text",
    "content": "walaupun yang tipsal KWKW",
    "url": null,
    "timestamp": "2026-04-23T11:34:53.940000+00:00",
    "channel_id": "1484896114762317994"
  },
  {
    "media_type": "text",
    "content": "jujur seru banget vc kali ini!",
    "url": null,
    "timestamp": "2026-04-23T11:35:13.001000+00:00",
    "channel_id": "1484896114762317994"
  },
  {
    "media_type": "text",
    "content": "sesi 1 diisi adikadik\nsesi 2 diisi kakakkakak\nsesi 3 diisi omom\nWKWKWKW 🤭",
    "url": null,
    "timestamp": "2026-04-23T11:35:14.313000+00:00",
    "channel_id": "1484896114762317994"
  },
  {
    "media_type": "text",
    "content": "jujur sekarang kalian jadi terbagi menjadi beberapa kelompok gini 😌",
    "url": null,
    "timestamp": "2026-04-23T11:35:15.813000+00:00",
    "channel_id": "1484896114762317994"
  },
  {
    "media_type": "text",
    "content": "tapi seneng deh aku jadi lebih gampang ingetnya",
    "url": null,
    "timestamp": "2026-04-23T11:35:17.278000+00:00",
    "channel_id": "1484896114762317994"
  },
  {
    "media_type": "text",
    "content": "jadi kamu tadi masuk sesi manaa??",
    "url": null,
    "timestamp": "2026-04-23T11:35:18.843000+00:00",
    "channel_id": "1484896114762317994"
  },
  {
    "media_type": "text",
    "content": "makasih ya sudah menyempatkan waktuuu",
    "url": null,
    "timestamp": "2026-04-23T11:35:20.358000+00:00",
    "channel_id": "1484896114762317994"
  },
  {
    "media_type": "text",
    "content": "akuuu senengg bangettt ketemuu lagii!",
    "url": null,
    "timestamp": "2026-04-23T11:35:22.263000+00:00",
    "channel_id": "1484896114762317994"
  },
  {
    "media_type": "text",
    "content": "makasih juga yang udah dm sebelum VC walaupun kadang aku juga lupa walaupun udah baca 🥹",
    "url": null,
    "timestamp": "2026-04-23T11:35:23.683000+00:00",
    "channel_id": "1484896114762317994"
  },
  {
    "media_type": "text",
    "content": "makasihhh yaaa yang tadi di sekolah di rumah di kantor di perjalanan tetep mau ngobrol sama aku, yapping, deep talk, berkabar, dan merencanakan banyak hal lagi nanti ke depannya! JUJUR excited 🤗😊",
    "url": null,
    "timestamp": "2026-04-23T11:35:25.099000+00:00",
    "channel_id": "1484896114762317994"
  },
  {
    "media_type": "text",
    "content": "BONUS SONG TADI GIMANA",
    "url": null,
    "timestamp": "2026-04-23T11:35:26.644000+00:00",
    "channel_id": "1484896114762317994"
  },
  {
    "media_type": "text",
    "content": "KAN DIBILANG",
    "url": null,
    "timestamp": "2026-04-23T11:35:28.059000+00:00",
    "channel_id": "1484896114762317994"
  },
  {
    "media_type": "text",
    "content": "BANYAK YANG SUKA KWKWKW",
    "url": null,
    "timestamp": "2026-04-23T11:35:29.461000+00:00",
    "channel_id": "1484896114762317994"
  },
  {
    "media_type": "text",
    "content": "aku liat yah editan kalian yang bilang ga ada member yang mau bonus song",
    "url": null,
    "timestamp": "2026-04-23T11:35:30.880000+00:00",
    "channel_id": "1484896114762317994"
  },
  {
    "media_type": "text",
    "content": "akan ku paksakan sampai bonus song itu bergema di teater 🎵🎤🎙️",
    "url": null,
    "timestamp": "2026-04-23T11:35:32.312000+00:00",
    "channel_id": "1484896114762317994"
  },
  {
    "media_type": "text",
    "content": "mau request?KWKWK",
    "url": null,
    "timestamp": "2026-04-23T11:35:33.736000+00:00",
    "channel_id": "1484896114762317994"
  },
  {
    "media_type": "text",
    "content": "makasih yang udah dukung akuuuu untukk nanti bisa bawain ame no pianist di RH",
    "url": null,
    "timestamp": "2026-04-23T11:35:35.102000+00:00",
    "channel_id": "1484896114762317994"
  },
  {
    "media_type": "text",
    "content": "kita usahakan yahh! 🫶",
    "url": null,
    "timestamp": "2026-04-23T11:35:36.506000+00:00",
    "channel_id": "1484896114762317994"
  },
  {
    "media_type": "text",
    "content": "kalau kita berusaha pasti bisa! kalau ada niatnya pasti bisa! kita berjuang bersama yah 👐",
    "url": null,
    "timestamp": "2026-04-23T11:35:37.826000+00:00",
    "channel_id": "1484896114762317994"
  },
  {
    "media_type": "text",
    "content": "jujur rate drama aku kmrn",
    "url": null,
    "timestamp": "2026-04-23T11:35:39.157000+00:00",
    "channel_id": "1484896114762317994"
  },
  {
    "media_type": "video",
    "content": "jujur ini awalnya kirain bakal foto 🥹🫵",
    "url": "https://raw.githubusercontent.com/dmkr48/gen11/main/media/1484896114762317994/e5dc25120384.mp4",
    "timestamp": "2026-04-23T11:35:43.282000+00:00",
    "channel_id": "1484896114762317994"
  },
  {
    "media_type": "image",
    "content": "tebak rasa apaaa??",
    "url": "https://raw.githubusercontent.com/dmkr48/gen11/main/media/1484896114762317994/a3ce4672a8aa.jpg",
    "timestamp": "2026-04-23T11:36:16.879000+00:00",
    "channel_id": "1484896114762317994"
  },
  {
    "media_type": "text",
    "content": "i start the day tadi dengan makan yoghurt!",
    "url": null,
    "timestamp": "2026-04-23T11:36:18.374000+00:00",
    "channel_id": "1484896114762317994"
  },
  {
    "media_type": "image",
    "content": "di bawahnya ada fruit bits yang enakkk XIIXXI",
    "url": "https://raw.githubusercontent.com/dmkr48/gen11/main/media/1484896114762317994/775123f51338.jpg",
    "timestamp": "2026-04-23T11:36:22.226000+00:00",
    "channel_id": "1484896114762317994"
  },
  {
    "media_type": "image",
    "content": "akuuu makan iniii! tau gak apa inii? rice cup rasa claypot! jujurrrrr penasaran sama rasanya KWKWK kamu tau kan aku sekepo itu pengen coba ini itu 😁",
    "url": "https://raw.githubusercontent.com/dmkr48/gen11/main/media/1484896114762317994/7fd6df3b95df.jpg",
    "timestamp": "2026-04-23T11:36:26.963000+00:00",
    "channel_id": "1484896114762317994"
  },
  {
    "media_type": "text",
    "content": "SEBENERNYA AKU AGAK MERAGUKAN TAKUT NASINYA GA MATENGG",
    "url": null,
    "timestamp": "2026-04-23T11:36:28.437000+00:00",
    "channel_id": "1484896114762317994"
  },
  {
    "media_type": "text",
    "content": "karena buliran ricenya kecil banget gituu!",
    "url": null,
    "timestamp": "2026-04-23T11:36:29.915000+00:00",
    "channel_id": "1484896114762317994"
  },
  {
    "media_type": "text",
    "content": "karena trust issue aku itu aku tambahin lagi air nya sedikit lebih banyak daripada anjuran 🙊",
    "url": null,
    "timestamp": "2026-04-23T11:36:31.351000+00:00",
    "channel_id": "1484896114762317994"
  },
  {
    "media_type": "text",
    "content": "tapi akhirnya aman aja kok dan nasinya matang sempurna yeyy 👏🎉🥳",
    "url": null,
    "timestamp": "2026-04-23T11:36:32.831000+00:00",
    "channel_id": "1484896114762317994"
  },
  {
    "media_type": "text",
    "content": "btw makannya bisa juga ditambahin topping kayak telur, sayuran atau apapun sesuka hati kalian",
    "url": null,
    "timestamp": "2026-04-23T11:36:34.276000+00:00",
    "channel_id": "1484896114762317994"
  },
  {
    "media_type": "text",
    "content": "YESH",
    "url": null,
    "timestamp": "2026-04-23T11:36:35.636000+00:00",
    "channel_id": "1484896114762317994"
  },
  {
    "media_type": "text",
    "content": "NEXT MAU COBA APALAGI!?",
    "url": null,
    "timestamp": "2026-04-23T11:36:37.070000+00:00",
    "channel_id": "1484896114762317994"
  },
  {
    "media_type": "text",
    "content": "COBA! KALIAN NGOMONGIN APA AJA SIH KEMARIN DI SESI MEETING 🤗🤗🤗",
    "url": null,
    "timestamp": "2026-04-23T11:36:38.406000+00:00",
    "channel_id": "1484896114762317994"
  },
  {
    "media_type": "text",
    "content": "mau tau dong",
    "url": null,
    "timestamp": "2026-04-23T11:36:39.881000+00:00",
    "channel_id": "1484896114762317994"
  },
  {
    "media_type": "text",
    "content": "ngomongin aku yang baik” kan",
    "url": null,
    "timestamp": "2026-04-23T11:36:41.334000+00:00",
    "channel_id": "1484896114762317994"
  },
  {
    "media_type": "text",
    "content": "🫵😊",
    "url": null,
    "timestamp": "2026-04-23T11:36:42.703000+00:00",
    "channel_id": "1484896114762317994"
  },
  {
    "media_type": "text",
    "content": "spill dikit dong",
    "url": null,
    "timestamp": "2026-04-23T11:36:44.248000+00:00",
    "channel_id": "1484896114762317994"
  },
  {
    "media_type": "text",
    "content": "BTW Baru inget kan mau live nya kids friendly ya kemarin",
    "url": null,
    "timestamp": "2026-04-23T11:36:45.687000+00:00",
    "channel_id": "1484896114762317994"
  },
  {
    "media_type": "text",
    "content": "tapi endingnya aku malah drama teatrikal main piano imaginer 🎹",
    "url": null,
    "timestamp": "2026-04-23T11:36:46.971000+00:00",
    "channel_id": "1484896114762317994"
  },
  {
    "media_type": "text",
    "content": "hmm",
    "url": null,
    "timestamp": "2026-04-23T11:36:48.410000+00:00",
    "channel_id": "1484896114762317994"
  },
  {
    "media_type": "text",
    "content": "jadi karena penonton viewersku terbagi dari yang kicil baget sampe yang … banget",
    "url": null,
    "timestamp": "2026-04-23T11:36:49.643000+00:00",
    "channel_id": "1484896114762317994"
  },
  {
    "media_type": "text",
    "content": "jadi sekarang live aku akan kids friendly dulu awalnya 😊",
    "url": null,
    "timestamp": "2026-04-23T11:37:16.555000+00:00",
    "channel_id": "1484896114762317994"
  },
  {
    "media_type": "text",
    "content": "jadi no marahmarah ya guys",
    "url": null,
    "timestamp": "2026-04-23T11:37:18.017000+00:00",
    "channel_id": "1484896114762317994"
  },
  {
    "media_type": "text",
    "content": "habis itu pertengahan pasti sudah ada percikan  🧨 ⚡️",
    "url": null,
    "timestamp": "2026-04-23T11:37:19.511000+00:00",
    "channel_id": "1484896114762317994"
  },
  {
    "media_type": "text",
    "content": "ya percik kecil meredup sendirinya lah",
    "url": null,
    "timestamp": "2026-04-23T11:37:20.969000+00:00",
    "channel_id": "1484896114762317994"
  },
  {
    "media_type": "text",
    "content": "habis itu tunggu dedek” baru tidur barulah kita masuk ke puncak acara 😊😊",
    "url": null,
    "timestamp": "2026-04-23T11:37:22.420000+00:00",
    "channel_id": "1484896114762317994"
  },
  {
    "media_type": "text",
    "content": "sekian infonya",
    "url": null,
    "timestamp": "2026-04-23T11:37:23.810000+00:00",
    "channel_id": "1484896114762317994"
  },
  {
    "media_type": "text",
    "content": "ditunggu live aku selanjutnya yah",
    "url": null,
    "timestamp": "2026-04-23T11:37:25.054000+00:00",
    "channel_id": "1484896114762317994"
  },
  {
    "media_type": "text",
    "content": "HUELOOO",
    "url": null,
    "timestamp": "2026-04-23T11:37:26.515000+00:00",
    "channel_id": "1484896114762317994"
  },
  {
    "media_type": "text",
    "content": "berikut beberapa hal yang akan membuatku bahagia",
    "url": null,
    "timestamp": "2026-04-23T11:37:28.080000+00:00",
    "channel_id": "1484896114762317994"
  },
  {
    "media_type": "image",
    "content": "SUKA KAN DENGAN CHOCOMINTO ? 😌😌",
    "url": "https://raw.githubusercontent.com/dmkr48/gen11/main/media/1484896114762317994/65f7dae56b4c.jpg",
    "timestamp": "2026-04-23T11:37:31.980000+00:00",
    "channel_id": "1484896114762317994"
  },
  {
    "media_type": "image",
    "content": "CHOCOMINTO",
    "url": "https://raw.githubusercontent.com/dmkr48/gen11/main/media/1484896114762317994/d38d94ffcd15.jpg",
    "timestamp": "2026-04-23T11:37:34.682000+00:00",
    "channel_id": "1484896114762317994"
  },
  {
    "media_type": "image",
    "content": "KOPIII YAAMPUN KOPIII JANGAN LUPA MINUM KOPI ☕️",
    "url": "https://raw.githubusercontent.com/dmkr48/gen11/main/media/1484896114762317994/26566c3c519f.jpg",
    "timestamp": "2026-04-23T11:37:38.478000+00:00",
    "channel_id": "1484896114762317994"
  },
  {
    "media_type": "text",
    "content": "KAMUUU UDAH MAM APA AJA HARI INI?",
    "url": null,
    "timestamp": "2026-04-23T11:37:39.941000+00:00",
    "channel_id": "1484896114762317994"
  },
  {
    "media_type": "text",
    "content": "dan hari ini ngapain ajaa?",
    "url": null,
    "timestamp": "2026-04-23T11:37:41.389000+00:00",
    "channel_id": "1484896114762317994"
  },
  {
    "media_type": "text",
    "content": "semangat yaw semoga lancar semua kegiatannyaaa",
    "url": null,
    "timestamp": "2026-04-23T11:37:42.783000+00:00",
    "channel_id": "1484896114762317994"
  },
  {
    "media_type": "text",
    "content": "doakan aku juga",
    "url": null,
    "timestamp": "2026-04-23T11:37:44.171000+00:00",
    "channel_id": "1484896114762317994"
  },
  {
    "media_type": "text",
    "content": "kita berdua saling mendoaakan ☺️",
    "url": null,
    "timestamp": "2026-04-23T11:37:46.101000+00:00",
    "channel_id": "1484896114762317994"
  },
  {
    "media_type": "text",
    "content": "kemarin hujan tapi ada yang kurang deh, apa ya yang kurang? 🥹",
    "url": null,
    "timestamp": "2026-04-23T11:37:47.470000+00:00",
    "channel_id": "1484896114762317994"
  },
  {
    "media_type": "text",
    "content": "aku sedang mengumpulkan 1001 tiktok untuk dibuat bareng alya elin 😌😌😌🫵",
    "url": null,
    "timestamp": "2026-04-23T11:37:48.813000+00:00",
    "channel_id": "1484896114762317994"
  },
  {
    "media_type": "text",
    "content": "Yaampun gemes banget dedekdedek aku udah ngabarin udah pada pulang sekolah yahh! Seru banget sih kegiatannya dek! Habis ekskul terus ada les lagi yah?? 😊😊 semangat yah dulu aku juga gitu dek 8 tahun lalu 😊 walaupun capek semangat ya dek 🥳🥳 SERU BANGETTTTTT nanti cerita lagi yahh ada kejadian apa hari ini di sekolahh 🤗",
    "url": null,
    "timestamp": "2026-04-23T11:37:50.274000+00:00",
    "channel_id": "1484896114762317994"
  },
  {
    "media_type": "text",
    "content": "pengen tau deh 😌",
    "url": null,
    "timestamp": "2026-04-23T11:38:18.161000+00:00",
    "channel_id": "1484896114762317994"
  },
  {
    "media_type": "text",
    "content": "SEBERAPA BANYAK SIHH yang besok ketemu di percin 😌🫵",
    "url": null,
    "timestamp": "2026-04-23T11:38:19.634000+00:00",
    "channel_id": "1484896114762317994"
  },
  {
    "media_type": "text",
    "content": "SEBERAPAA BANYAK SIH yangg nungguin aku shonichi Ramune Team lovee ❤️❤️❤️",
    "url": null,
    "timestamp": "2026-04-23T11:38:20.975000+00:00",
    "channel_id": "1484896114762317994"
  },
  {
    "media_type": "text",
    "content": "SIAPA YANG KETEMUU AKUU LAGI HARI MINGGUU??",
    "url": null,
    "timestamp": "2026-04-23T11:38:22.284000+00:00",
    "channel_id": "1484896114762317994"
  },
  {
    "media_type": "image",
    "content": "[photo]",
    "url": "https://raw.githubusercontent.com/dmkr48/gen11/main/media/1484896114762317994/e87468f851c7.jpg",
    "timestamp": "2026-04-23T11:38:26.298000+00:00",
    "channel_id": "1484896114762317994"
  },
  {
    "media_type": "text",
    "content": "inilah yang dinamakan bonus foto PM ☺️",
    "url": null,
    "timestamp": "2026-04-23T11:38:27.946000+00:00",
    "channel_id": "1484896114762317994"
  },
  {
    "media_type": "text",
    "content": "Tadi aku nyusul dateng ke makanmakan team love soalnya ada kegiatan duluuu 🥹",
    "url": null,
    "timestamp": "2026-04-23T11:38:29.423000+00:00",
    "channel_id": "1484896114762317994"
  },
  {
    "media_type": "image",
    "content": "ini lucu kayak bubbles bubbles semua!",
    "url": "https://raw.githubusercontent.com/dmkr48/gen11/main/media/1484896114762317994/bcdff089c47a.jpg",
    "timestamp": "2026-04-23T11:38:32.709000+00:00",
    "channel_id": "1484896114762317994"
  },
  {
    "media_type": "image",
    "content": "kirain ini bag nya isinya ga ada orang nya eh ternyata ada penghuninya 😳",
    "url": "https://raw.githubusercontent.com/dmkr48/gen11/main/media/1484896114762317994/150a5d179ca2.jpg",
    "timestamp": "2026-04-23T11:38:36.623000+00:00",
    "channel_id": "1484896114762317994"
  },
  {
    "media_type": "image",
    "content": "perintil gemes, masa tempat tidur jadi gantungan 🥹",
    "url": "https://raw.githubusercontent.com/dmkr48/gen11/main/media/1484896114762317994/1409a0e164ee.jpg",
    "timestamp": "2026-04-23T11:38:41.055000+00:00",
    "channel_id": "1484896114762317994"
  },
  {
    "media_type": "text",
    "content": "yah biasalah cewe suka fotoin perintilperintilan",
    "url": null,
    "timestamp": "2026-04-23T11:38:42.588000+00:00",
    "channel_id": "1484896114762317994"
  },
  {
    "media_type": "text",
    "content": "akhirnya Qtime sama team love 🫵😊",
    "url": null,
    "timestamp": "2026-04-23T11:38:44.053000+00:00",
    "channel_id": "1484896114762317994"
  },
  {
    "media_type": "text",
    "content": "AZIK",
    "url": null,
    "timestamp": "2026-04-23T11:38:45.478000+00:00",
    "channel_id": "1484896114762317994"
  },
  {
    "media_type": "text",
    "content": "tadi photobox liat ga sih",
    "url": null,
    "timestamp": "2026-04-23T11:38:46.842000+00:00",
    "channel_id": "1484896114762317994"
  },
  {
    "media_type": "text",
    "content": "SEHEBOH ITU KITA",
    "url": null,
    "timestamp": "2026-04-23T11:38:48.335000+00:00",
    "channel_id": "1484896114762317994"
  },
  {
    "media_type": "text",
    "content": "WKWKKW",
    "url": null,
    "timestamp": "2026-04-23T11:38:49.665000+00:00",
    "channel_id": "1484896114762317994"
  },
  {
    "media_type": "image",
    "content": "[photo]",
    "url": "https://raw.githubusercontent.com/dmkr48/gen11/main/media/1484896114762317994/e264917bfd7f.jpg",
    "timestamp": "2026-04-23T11:38:53.391000+00:00",
    "channel_id": "1484896114762317994"
  },
  {
    "media_type": "text",
    "content": "terus aku belum makan malem kan jadinya malemnya lagih aku makan buanyak pls ini kenyang bgt",
    "url": null,
    "timestamp": "2026-04-23T11:38:54.912000+00:00",
    "channel_id": "1484896114762317994"
  },
  {
    "media_type": "text",
    "content": "how’s ur dayyyyy",
    "url": null,
    "timestamp": "2026-04-23T11:38:56.312000+00:00",
    "channel_id": "1484896114762317994"
  },
  {
    "media_type": "text",
    "content": "semoga hari ini menyenangkan yah!!",
    "url": null,
    "timestamp": "2026-04-23T11:38:57.708000+00:00",
    "channel_id": "1484896114762317994"
  },
  {
    "media_type": "text",
    "content": "walaupun kurang pun tidak apaapa, tidak semua hari harus selalu baik yang penting kita menjadi manusia yang selalu berprogress dan belajar setiap harinya! Jangan lupa bersyukur juga yah! 😊",
    "url": null,
    "timestamp": "2026-04-23T11:39:19.731000+00:00",
    "channel_id": "1484896114762317994"
  },
  {
    "media_type": "text",
    "content": "aku selalu bersyukur punya kalian",
    "url": null,
    "timestamp": "2026-04-23T11:39:21.136000+00:00",
    "channel_id": "1484896114762317994"
  },
  {
    "media_type": "text",
    "content": "REAL INI MAH REAL BRO 😎",
    "url": null,
    "timestamp": "2026-04-23T11:39:22.514000+00:00",
    "channel_id": "1484896114762317994"
  },
  {
    "media_type": "text",
    "content": "halo bagaimana kegiatannya sejauh inii?",
    "url": null,
    "timestamp": "2026-04-23T11:39:23.895000+00:00",
    "channel_id": "1484896114762317994"
  },
  {
    "media_type": "text",
    "content": "semangat ya sampe malammmmm!",
    "url": null,
    "timestamp": "2026-04-23T11:39:25.257000+00:00",
    "channel_id": "1484896114762317994"
  },
  {
    "media_type": "text",
    "content": "nanti ketemu jam 7!",
    "url": null,
    "timestamp": "2026-04-23T11:39:26.640000+00:00",
    "channel_id": "1484896114762317994"
  },
  {
    "media_type": "text",
    "content": "sudah menentukan bonus song yang akan aku bawakan hari ini 😌😌😌",
    "url": null,
    "timestamp": "2026-04-23T11:39:28.076000+00:00",
    "channel_id": "1484896114762317994"
  },
  {
    "media_type": "text",
    "content": "BTW",
    "url": null,
    "timestamp": "2026-04-23T11:39:29.546000+00:00",
    "channel_id": "1484896114762317994"
  },
  {
    "media_type": "text",
    "content": "AKU KAYAKNYA EMANG SUKA BANGET WANGI MANISSS TAUU",
    "url": null,
    "timestamp": "2026-04-23T11:39:30.875000+00:00",
    "channel_id": "1484896114762317994"
  },
  {
    "media_type": "text",
    "content": "aku habis makan dubai chewy cookie yang di mall yang katanya ngantri tapi kemarin ga sengantri itu sih",
    "url": null,
    "timestamp": "2026-04-23T11:39:32.311000+00:00",
    "channel_id": "1484896114762317994"
  },
  {
    "media_type": "image",
    "content": "jujur ini lebih lembek teksturnya daripada ka manda",
    "url": "https://raw.githubusercontent.com/dmkr48/gen11/main/media/1484896114762317994/4d1041b998d4.jpg",
    "timestamp": "2026-04-23T11:39:36.527000+00:00",
    "channel_id": "1484896114762317994"
  },
  {
    "media_type": "text",
    "content": "dubai chewy yang jauh berbeda rasanya",
    "url": null,
    "timestamp": "2026-04-23T11:39:38.184000+00:00",
    "channel_id": "1484896114762317994"
  },
  {
    "media_type": "text",
    "content": "kalau punya ka manda lebih padet",
    "url": null,
    "timestamp": "2026-04-23T11:39:39.730000+00:00",
    "channel_id": "1484896114762317994"
  },
  {
    "media_type": "text",
    "content": "tapi tetep tergantung selera",
    "url": null,
    "timestamp": "2026-04-23T11:39:41.215000+00:00",
    "channel_id": "1484896114762317994"
  },
  {
    "media_type": "text",
    "content": "tapi aku akan re order yang punya ka manda",
    "url": null,
    "timestamp": "2026-04-23T11:39:42.637000+00:00",
    "channel_id": "1484896114762317994"
  },
  {
    "media_type": "text",
    "content": "AMANDA COOKIES JAYAJAYAJAYA",
    "url": null,
    "timestamp": "2026-04-23T11:39:44.097000+00:00",
    "channel_id": "1484896114762317994"
  },
  {
    "media_type": "image",
    "content": "packagingnya ada boxnya",
    "url": "https://raw.githubusercontent.com/dmkr48/gen11/main/media/1484896114762317994/278504f1e09d.jpg",
    "timestamp": "2026-04-23T11:39:47.459000+00:00",
    "channel_id": "1484896114762317994"
  },
  {
    "media_type": "text",
    "content": "wiw heboh sekali",
    "url": null,
    "timestamp": "2026-04-23T11:39:49.026000+00:00",
    "channel_id": "1484896114762317994"
  },
  {
    "media_type": "text",
    "content": "btw aku ada beli mainan",
    "url": null,
    "timestamp": "2026-04-23T11:39:53.046000+00:00",
    "channel_id": "1484896114762317994"
  },
  {
    "media_type": "text",
    "content": "WKKWWKKW",
    "url": null,
    "timestamp": "2026-04-23T11:39:54.528000+00:00",
    "channel_id": "1484896114762317994"
  },
  {
    "media_type": "text",
    "content": "tapi belum aku unboxing",
    "url": null,
    "timestamp": "2026-04-23T11:40:21.727000+00:00",
    "channel_id": "1484896114762317994"
  },
  {
    "media_type": "text",
    "content": "nanti yah",
    "url": null,
    "timestamp": "2026-04-23T11:40:23.231000+00:00",
    "channel_id": "1484896114762317994"
  },
  {
    "media_type": "text",
    "content": "biar surpris",
    "url": null,
    "timestamp": "2026-04-23T11:40:24.730000+00:00",
    "channel_id": "1484896114762317994"
  },
  {
    "media_type": "image",
    "content": "[photo]",
    "url": "https://raw.githubusercontent.com/dmkr48/gen11/main/media/1484896114762317994/73ea7baf2c24.jpg",
    "timestamp": "2026-04-23T11:40:28.502000+00:00",
    "channel_id": "1484896114762317994"
  },
  {
    "media_type": "image",
    "content": "[photo]",
    "url": "https://raw.githubusercontent.com/dmkr48/gen11/main/media/1484896114762317994/219f7de7ec13.jpg",
    "timestamp": "2026-04-23T11:40:32.405000+00:00",
    "channel_id": "1484896114762317994"
  },
  {
    "media_type": "image",
    "content": "[photo]",
    "url": "https://raw.githubusercontent.com/dmkr48/gen11/main/media/1484896114762317994/d1bec0d5c7e9.jpg",
    "timestamp": "2026-04-23T11:40:36.147000+00:00",
    "channel_id": "1484896114762317994"
  },
  {
    "media_type": "image",
    "content": "[photo]",
    "url": "https://raw.githubusercontent.com/dmkr48/gen11/main/media/1484896114762317994/5d7a78fa99c6.jpg",
    "timestamp": "2026-04-23T11:40:40.026000+00:00",
    "channel_id": "1484896114762317994"
  },
  {
    "media_type": "image",
    "content": "thankkk youuu yah percinnya! seneng kemarin banyak mata yang aku kenal jadi seru hi bye nya! makasih yang udah panggil aku jugak! 🫰😊 semoga ketemu lagiii besok!",
    "url": "https://raw.githubusercontent.com/dmkr48/gen11/main/media/1484896114762317994/685720779565.jpg",
    "timestamp": "2026-04-23T11:40:44.427000+00:00",
    "channel_id": "1484896114762317994"
  },
  {
    "media_type": "image",
    "content": "ini foto di X tapi versi lebih BESAR",
    "url": "https://raw.githubusercontent.com/dmkr48/gen11/main/media/1484896114762317994/c37e0a0c7321.jpg",
    "timestamp": "2026-04-23T11:40:48.573000+00:00",
    "channel_id": "1484896114762317994"
  },
  {
    "media_type": "image",
    "content": "[photo]",
    "url": "https://raw.githubusercontent.com/dmkr48/gen11/main/media/1484896114762317994/fcf11800ca36.jpg",
    "timestamp": "2026-04-23T11:40:52.262000+00:00",
    "channel_id": "1484896114762317994"
  },
  {
    "media_type": "image",
    "content": "[photo]",
    "url": "https://raw.githubusercontent.com/dmkr48/gen11/main/media/1484896114762317994/77137fcc93da.jpg",
    "timestamp": "2026-04-23T11:40:55.724000+00:00",
    "channel_id": "1484896114762317994"
  },
  {
    "media_type": "text",
    "content": "thanks a lot kemarin seru bangett! semoga seru juga buat kalian 😊",
    "url": null,
    "timestamp": "2026-04-23T11:40:57.219000+00:00",
    "channel_id": "1484896114762317994"
  },
  {
    "media_type": "image",
    "content": "[photo]",
    "url": "https://raw.githubusercontent.com/dmkr48/gen11/main/media/1484896114762317994/36b3a3037422.jpg",
    "timestamp": "2026-04-23T11:41:00.386000+00:00",
    "channel_id": "1484896114762317994"
  },
  {
    "media_type": "text",
    "content": "semua akan team love pada waktunya",
    "url": null,
    "timestamp": "2026-04-23T11:41:02.019000+00:00",
    "channel_id": "1484896114762317994"
  },
  {
    "media_type": "text",
    "content": "btw ada yang mau request rambut untuk besok ramune??😊😊",
    "url": null,
    "timestamp": "2026-04-23T11:41:03.469000+00:00",
    "channel_id": "1484896114762317994"
  },
  {
    "media_type": "text",
    "content": "Yang paling penting harus jadi diri yang ga cari sensasi 😌",
    "url": null,
    "timestamp": "2026-04-23T11:41:04.850000+00:00",
    "channel_id": "1484896114762317994"
  },
  {
    "media_type": "text",
    "content": "lempar batu sembunyi tangan di krumunan orang 🤭🪨",
    "url": null,
    "timestamp": "2026-04-23T11:41:06.230000+00:00",
    "channel_id": "1484896114762317994"
  },
  {
    "media_type": "text",
    "content": "JANGAN LUPA STREAM #WAKAKA PEOPLE",
    "url": null,
    "timestamp": "2026-04-23T11:41:07.632000+00:00",
    "channel_id": "1484896114762317994"
  },
  {
    "media_type": "text",
    "content": "HEYYY SUDAH MENDEKATI KETEMU LAGI 😌🫰🫰🫰🫰",
    "url": null,
    "timestamp": "2026-04-23T11:41:09.038000+00:00",
    "channel_id": "1484896114762317994"
  },
  {
    "media_type": "image",
    "content": "jajan sama anindy",
    "url": "https://raw.githubusercontent.com/dmkr48/gen11/main/media/1484896114762317994/039b1e2d3536.jpg",
    "timestamp": "2026-04-23T11:41:12.548000+00:00",
    "channel_id": "1484896114762317994"
  },
  {
    "media_type": "text",
    "content": "AYAM YANG 20 CM ITU",
    "url": null,
    "timestamp": "2026-04-23T11:41:25.570000+00:00",
    "channel_id": "1484896114762317994"
  },
  {
    "media_type": "image",
    "content": "ini kombucha rasa raspberry",
    "url": "https://raw.githubusercontent.com/dmkr48/gen11/main/media/1484896114762317994/e9a7866e1114.jpg",
    "timestamp": "2026-04-23T11:41:29.233000+00:00",
    "channel_id": "1484896114762317994"
  },
  {
    "media_type": "text",
    "content": "YANG WAKTU ITU AKU SPILL DI LIVE PAS DI VIETNAM",
    "url": null,
    "timestamp": "2026-04-23T11:41:30.797000+00:00",
    "channel_id": "1484896114762317994"
  },
  {
    "media_type": "text",
    "content": "MERAH BANGET IYA TAU",
    "url": null,
    "timestamp": "2026-04-23T11:41:32.113000+00:00",
    "channel_id": "1484896114762317994"
  },
  {
    "media_type": "text",
    "content": "TAPI ENAK LOCH",
    "url": null,
    "timestamp": "2026-04-23T11:41:33.459000+00:00",
    "channel_id": "1484896114762317994"
  },
  {
    "media_type": "image",
    "content": "menikmati performance team DREAM",
    "url": "https://raw.githubusercontent.com/dmkr48/gen11/main/media/1484896114762317994/1590ba740902.jpg",
    "timestamp": "2026-04-23T11:41:36.602000+00:00",
    "channel_id": "1484896114762317994"
  },
  {
    "media_type": "image",
    "content": "🖤🖤🖤",
    "url": "https://raw.githubusercontent.com/dmkr48/gen11/main/media/1484896114762317994/cc9c96070964.jpg",
    "timestamp": "2026-04-23T11:41:39.558000+00:00",
    "channel_id": "1484896114762317994"
  },
  {
    "media_type": "text",
    "content": "JUJUR PENGEN BANGET JUGA NONTON BARCA MADRID WKWKW",
    "url": null,
    "timestamp": "2026-04-23T11:41:41.014000+00:00",
    "channel_id": "1484896114762317994"
  },
  {
    "media_type": "image",
    "content": "semoga nanti kita bisa ketemu lagi yah di FINLAND 😊😊",
    "url": "https://raw.githubusercontent.com/dmkr48/gen11/main/media/1484896114762317994/dce9b374b6cf.jpg",
    "timestamp": "2026-04-23T11:41:44.558000+00:00",
    "channel_id": "1484896114762317994"
  },
  {
    "media_type": "image",
    "content": "jujur seneng banget bawain finland miracle sama cepio keti (marah kecil sama keti. 😤",
    "url": "https://raw.githubusercontent.com/dmkr48/gen11/main/media/1484896114762317994/a4ec525e2ee8.jpg",
    "timestamp": "2026-04-23T11:41:48.648000+00:00",
    "channel_id": "1484896114762317994"
  },
  {
    "media_type": "image",
    "content": "terima kasih Ramune hari ini yahh! 😊😊😊",
    "url": "https://raw.githubusercontent.com/dmkr48/gen11/main/media/1484896114762317994/2eb41d535f03.jpg",
    "timestamp": "2026-04-23T11:41:52.476000+00:00",
    "channel_id": "1484896114762317994"
  },
  {
    "media_type": "image",
    "content": "gimana finland hijaunyaa?",
    "url": "https://raw.githubusercontent.com/dmkr48/gen11/main/media/1484896114762317994/26faadd93afc.jpg",
    "timestamp": "2026-04-23T11:41:56.739000+00:00",
    "channel_id": "1484896114762317994"
  },
  {
    "media_type": "text",
    "content": "makasihhhh yaah yang udah ketemuu! jujur seneng dan sekarang selalu nunggu” ketemu lagi karena seneng bisa perform lagi bisa bawel in kalian dan bisa liat muka kalian lagii!",
    "url": null,
    "timestamp": "2026-04-23T11:41:58.297000+00:00",
    "channel_id": "1484896114762317994"
  },
  {
    "media_type": "text",
    "content": "jujur sedih banget adik kecil gen 11 umumin grad lagi tapi seneng juga karena dia akan mendapatkan sinar di tempat lain yang dia tuju nantii! 😊",
    "url": null,
    "timestamp": "2026-04-23T11:41:59.622000+00:00",
    "channel_id": "1484896114762317994"
  },
  {
    "media_type": "text",
    "content": "Setuju banget kata cathy banyak momen yang bikin sedih, senang , kecewa, terharu, deg-degan yang kita lewati bersama, jujur banyak banget jerih payah selama di sini bareng kalian tapi itu juga yang membuat aku mejadi tambah semangat dan aku merasa perjalanan aku masih belum selesai, dengan semua jerih payah yang aku lewatkan, aku mau nantinya akan menyambut masa-masa yang bersinar juga sama kalian!",
    "url": null,
    "timestamp": "2026-04-23T11:42:01.001000+00:00",
    "channel_id": "1484896114762317994"
  },
  {
    "media_type": "text",
    "content": "Aku mau berjuang bersama kaliann! Mohon dukungannya untuk ke depannyaa yaa 🥹🥹 Kalau kalian juga sedang merasa lelah, jangan lupa istirahat yah! Tapi tetap ingat tujuan awal kalian yah",
    "url": null,
    "timestamp": "2026-04-23T11:42:02.397000+00:00",
    "channel_id": "1484896114762317994"
  },
  {
    "media_type": "text",
    "content": "MAKASSIIYII YAA TADIII IDN LIVENYA?",
    "url": null,
    "timestamp": "2026-04-23T11:42:04.019000+00:00",
    "channel_id": "1484896114762317994"
  },
  {
    "media_type": "text",
    "content": "!",
    "url": null,
    "timestamp": "2026-04-23T11:42:05.502000+00:00",
    "channel_id": "1484896114762317994"
  },
  {
    "media_type": "text",
    "content": "udah lama banget ga live",
    "url": null,
    "timestamp": "2026-04-23T11:42:06.912000+00:00",
    "channel_id": "1484896114762317994"
  },
  {
    "media_type": "text",
    "content": "jujur kangen",
    "url": null,
    "timestamp": "2026-04-23T11:42:08.423000+00:00",
    "channel_id": "1484896114762317994"
  },
  {
    "media_type": "text",
    "content": "DIKIT",
    "url": null,
    "timestamp": "2026-04-23T11:42:26.518000+00:00",
    "channel_id": "1484896114762317994"
  },
  {
    "media_type": "text",
    "content": "😊🤏",
    "url": null,
    "timestamp": "2026-04-23T11:42:28.016000+00:00",
    "channel_id": "1484896114762317994"
  },
  {
    "media_type": "text",
    "content": "MAKASIHHHHH YAA GUYSS DUKUNGANNYA BUAT AKU KEMARIN , Makasih yang udah tulis apre21oshi, makasih yang udah DM, Udah mention”, dan ngomongin aku jga di X, aku gpp kok seberapa kalian suka isengin aku jailin aku, becandain aku krn aku tau dalam lubuk hati terdalam kalian sayang sama aku ya kan 😌",
    "url": null,
    "timestamp": "2026-04-23T11:42:29.328000+00:00",
    "channel_id": "1484896114762317994"
  },
  {
    "media_type": "text",
    "content": "makasihhh jugaa yahh yang udah #cynabung, mau berterima kasih kepada kalian personally yang udah semangat banget membantu aku sampai nanti mencapai puncak gunung #cynabung ⛰️walaupun sambil diterpa hujan 🌧️🥹",
    "url": null,
    "timestamp": "2026-04-23T11:42:30.774000+00:00",
    "channel_id": "1484896114762317994"
  },
  {
    "media_type": "image",
    "content": "[photo]",
    "url": "https://raw.githubusercontent.com/dmkr48/gen11/main/media/1484896114762317994/e802df4add0a.jpg",
    "timestamp": "2026-04-23T11:42:33.355000+00:00",
    "channel_id": "1484896114762317994"
  },
  {
    "media_type": "image",
    "content": "[photo]",
    "url": "https://raw.githubusercontent.com/dmkr48/gen11/main/media/1484896114762317994/e955c3f73e4d.jpg",
    "timestamp": "2026-04-23T11:42:36.488000+00:00",
    "channel_id": "1484896114762317994"
  },
  {
    "media_type": "image",
    "content": "[photo]",
    "url": "https://raw.githubusercontent.com/dmkr48/gen11/main/media/1484896114762317994/64ba01f8cb1f.jpg",
    "timestamp": "2026-04-23T11:42:39.018000+00:00",
    "channel_id": "1484896114762317994"
  },
  {
    "media_type": "image",
    "content": "[photo]",
    "url": "https://raw.githubusercontent.com/dmkr48/gen11/main/media/1484896114762317994/3aef64751492.jpg",
    "timestamp": "2026-04-23T11:42:41.961000+00:00",
    "channel_id": "1484896114762317994"
  },
  {
    "media_type": "image",
    "content": "[photo]",
    "url": "https://raw.githubusercontent.com/dmkr48/gen11/main/media/1484896114762317994/d5a5f90ec7f1.jpg",
    "timestamp": "2026-04-23T11:42:45.069000+00:00",
    "channel_id": "1484896114762317994"
  },
  {
    "media_type": "image",
    "content": "[photo]",
    "url": "https://raw.githubusercontent.com/dmkr48/gen11/main/media/1484896114762317994/769128cbc7c1.jpg",
    "timestamp": "2026-04-23T11:42:47.838000+00:00",
    "channel_id": "1484896114762317994"
  },
  {
    "media_type": "text",
    "content": "GUYS AKUUU JADII TERTARIKK OLAHRAGA GNIII IHH 🫶🙆‍♀️",
    "url": null,
    "timestamp": "2026-04-23T11:42:49.383000+00:00",
    "channel_id": "1484896114762317994"
  },
  {
    "media_type": "text",
    "content": "udah lama ga nobar juga! PENGEN DEH NOBAR LAGI",
    "url": null,
    "timestamp": "2026-04-23T11:42:50.735000+00:00",
    "channel_id": "1484896114762317994"
  },
  {
    "media_type": "text",
    "content": "besok malam ada jadwal match apakah??",
    "url": null,
    "timestamp": "2026-04-23T11:42:52.178000+00:00",
    "channel_id": "1484896114762317994"
  },
  {
    "media_type": "text",
    "content": "sesungguhnya aku emang suka banget olahraga pas zaman-zaman sekolah",
    "url": null,
    "timestamp": "2026-04-23T11:42:53.582000+00:00",
    "channel_id": "1484896114762317994"
  },
  {
    "media_type": "text",
    "content": "tapi sekarang ingin ku tumbuhkan lagi semangat itu 🤩",
    "url": null,
    "timestamp": "2026-04-23T11:42:55.054000+00:00",
    "channel_id": "1484896114762317994"
  },
  {
    "media_type": "text",
    "content": "ASIKKK",
    "url": null,
    "timestamp": "2026-04-23T11:42:56.479000+00:00",
    "channel_id": "1484896114762317994"
  },
  {
    "media_type": "text",
    "content": "mana nih anak komunitas olahraga",
    "url": null,
    "timestamp": "2026-04-23T11:42:57.899000+00:00",
    "channel_id": "1484896114762317994"
  },
  {
    "media_type": "text",
    "content": "absen dulu cobak",
    "url": null,
    "timestamp": "2026-04-23T11:42:59.351000+00:00",
    "channel_id": "1484896114762317994"
  },
  {
    "media_type": "text",
    "content": "BTW karena pada bilang bagus an naikin distance, akan aku coba berikutnya ya! tapi disini dulu aja yang tau KWKWKWK",
    "url": null,
    "timestamp": "2026-04-23T11:43:00.723000+00:00",
    "channel_id": "1484896114762317994"
  },
  {
    "media_type": "text",
    "content": "nanti surprise aja 🫰🫰",
    "url": null,
    "timestamp": "2026-04-23T11:43:02.112000+00:00",
    "channel_id": "1484896114762317994"
  },
  {
    "media_type": "text",
    "content": "",
    "url": null,
    "timestamp": "2026-04-24T11:29:33.597000+00:00",
    "channel_id": "1484896114762317994"
  },
  {
    "media_type": "text",
    "content": "aku lagi nontonnnnn para perasuk! this is not a horror story tapi jujur nyeremin 😱😱",
    "url": null,
    "timestamp": "2026-04-24T14:11:43.760000+00:00",
    "channel_id": "1484896114762317994"
  },
  {
    "media_type": "text",
    "content": "tadi sempet nonton podcastnya sebelum nonton film! aku sekarang sering nonton podcast dulu supaya lebih ngerti kalo nonton! katanya its a movie abt realita kehidupan juga",
    "url": null,
    "timestamp": "2026-04-24T14:11:44.664000+00:00",
    "channel_id": "1484896114762317994"
  },
  {
    "media_type": "text",
    "content": "pas nonton lumayan banyak tahan nafas soalnya banyak yang WOW 😳😳😳",
    "url": null,
    "timestamp": "2026-04-24T14:11:45.712000+00:00",
    "channel_id": "1484896114762317994"
  },
  {
    "media_type": "text",
    "content": "tidak terexpect sekali",
    "url": null,
    "timestamp": "2026-04-24T14:11:46.652000+00:00",
    "channel_id": "1484896114762317994"
  },
  {
    "media_type": "text",
    "content": "jujur gabisa dijelasin KWKWKW",
    "url": null,
    "timestamp": "2026-04-24T14:11:47.822000+00:00",
    "channel_id": "1484896114762317994"
  },
  {
    "media_type": "text",
    "content": "sudah siap untuk team love besok?",
    "url": null,
    "timestamp": "2026-04-24T17:03:00.698000+00:00",
    "channel_id": "1484896114762317994"
  },
  {
    "media_type": "text",
    "content": "aku pengen banget menampilkan yang terbaik 🥺 mohon dukungannya ke depannya supaya aku bisa menampilkan yang terbaik yah! ☺️",
    "url": null,
    "timestamp": "2026-04-24T17:03:01.858000+00:00",
    "channel_id": "1484896114762317994"
  },
  {
    "media_type": "text",
    "content": "terima kasih dukungannyaa! sudah aku bacaa semuaa 🥹! sayang kalian semua! peluk jauhh 🤗",
    "url": null,
    "timestamp": "2026-04-25T05:58:13.764000+00:00",
    "channel_id": "1484896114762317994"
  },
  {
    "media_type": "image",
    "content": "INI MILKTEA YAAMPUN ENAK BGT 🤤 ini papa aku yang pesen, beliau pesan milk tea, jujur awalnya underestimate karena milk tea ka ada dimanamana yah tapi ini dapet caramel pudding gitu WOAW beneran gapernah makan caramel pudding se padet tapi selembut ini, literally wanna fly there lagi buat makan pudding ini 🥹berlebihan sih hehe",
    "url": "https://raw.githubusercontent.com/dmkr48/gen11/main/media/1484896114762317994/c5812e966e93.jpg",
    "timestamp": "2026-04-27T09:39:28.652000+00:00",
    "channel_id": "1484896114762317994"
  },
  {
    "media_type": "image",
    "content": "abis pulang dari perpus nih! aku anak ambis baca buku 10 jam di perpus",
    "url": "https://raw.githubusercontent.com/dmkr48/gen11/main/media/1484896114762317994/39556357fe3a.jpg",
    "timestamp": "2026-04-27T09:39:31.719000+00:00",
    "channel_id": "1484896114762317994"
  },
  {
    "media_type": "text",
    "content": "Semangat untuk hari ini!",
    "url": null,
    "timestamp": "2026-04-27T09:39:32.780000+00:00",
    "channel_id": "1484896114762317994"
  },
  {
    "media_type": "text",
    "content": "rate seberapa semangat hari iniiii!",
    "url": null,
    "timestamp": "2026-04-27T09:39:33.659000+00:00",
    "channel_id": "1484896114762317994"
  },
  {
    "media_type": "image",
    "content": "another pap habis lari!",
    "url": "https://raw.githubusercontent.com/dmkr48/gen11/main/media/1484896114762317994/e6b33a0ac788.jpg",
    "timestamp": "2026-04-28T06:30:37.413000+00:00",
    "channel_id": "1484896114762317994"
  },
  {
    "media_type": "text",
    "content": "UDAH POP POP DONG SEMANGATNYA KALAU GINI?",
    "url": null,
    "timestamp": "2026-04-28T06:30:37.972000+00:00",
    "channel_id": "1484896114762317994"
  },
  {
    "media_type": "text",
    "content": "Btw makasih udah dengerin live aku juga kemarin",
    "url": null,
    "timestamp": "2026-04-28T06:30:38.544000+00:00",
    "channel_id": "1484896114762317994"
  },
  {
    "media_type": "text",
    "content": "nanti mau live juga mungkin jam 6 sore gitu yahh",
    "url": null,
    "timestamp": "2026-04-28T06:30:38.897000+00:00",
    "channel_id": "1484896114762317994"
  },
  {
    "media_type": "text",
    "content": "pasang telinga pasang mata pasang alarm ⏰ pasang notification 📢🔔",
    "url": null,
    "timestamp": "2026-04-28T06:30:39.329000+00:00",
    "channel_id": "1484896114762317994"
  },
  {
    "media_type": "text",
    "content": "nanti mau bahas apalagi sich",
    "url": null,
    "timestamp": "2026-04-28T06:30:39.864000+00:00",
    "channel_id": "1484896114762317994"
  },
  {
    "media_type": "text",
    "content": "yang asikasikkk dong",
    "url": null,
    "timestamp": "2026-04-28T06:30:40.220000+00:00",
    "channel_id": "1484896114762317994"
  },
  {
    "media_type": "text",
    "content": "jangan lah kau bersedih diasikin aja 🤘",
    "url": null,
    "timestamp": "2026-04-28T06:30:40.704000+00:00",
    "channel_id": "1484896114762317994"
  },
  {
    "media_type": "text",
    "content": "btw makasih juga yang udah DM DM",
    "url": null,
    "timestamp": "2026-04-28T06:30:41.219000+00:00",
    "channel_id": "1484896114762317994"
  },
  {
    "media_type": "text",
    "content": "penyemangatku hari ini",
    "url": null,
    "timestamp": "2026-04-28T06:30:41.710000+00:00",
    "channel_id": "1484896114762317994"
  },
  {
    "media_type": "text",
    "content": "sebenernya dari kemarin untuk memicu semangat aku, aku banyak banget jajan tapi kalorinya dibakar dengan banyak kegiatan fisik juga kok",
    "url": null,
    "timestamp": "2026-04-28T06:30:42.160000+00:00",
    "channel_id": "1484896114762317994"
  },
  {
    "media_type": "text",
    "content": "halow!",
    "url": null,
    "timestamp": "2026-04-29T10:11:46.970000+00:00",
    "channel_id": "1484896114762317994"
  },
  {
    "media_type": "text",
    "content": "gimana hari inii?",
    "url": null,
    "timestamp": "2026-04-29T10:11:47.942000+00:00",
    "channel_id": "1484896114762317994"
  },
  {
    "media_type": "text",
    "content": "MAKACI YA YANG SELALU MENGIRIMKAN PESANNN",
    "url": null,
    "timestamp": "2026-04-29T10:11:48.593000+00:00",
    "channel_id": "1484896114762317994"
  },
  {
    "media_type": "text",
    "content": "di kala aku lagi butuh dukungan selalu banyak dukungan yang masukkkkk",
    "url": null,
    "timestamp": "2026-04-29T10:11:49.193000+00:00",
    "channel_id": "1484896114762317994"
  },
  {
    "media_type": "text",
    "content": "☺️☺️🫶",
    "url": null,
    "timestamp": "2026-04-29T10:11:49.896000+00:00",
    "channel_id": "1484896114762317994"
  }
]